[
  {
    "finess": "300003977",
    "raison_sociale": "SELARL PHARMACIE CATHALA",
    "numero voie": "2",
    "type_voie": "BD",
    "libelle_voie": "Diderot",
    "bp": "",
    "cp": "30220",
    "VILLE": "AIGUES MORTES",
    "tel": "466536800",
    "telecopie": "448060587",
    "categorie etablissement": "620",
    "libelle categorie": "Pharmacie d'Officine",
    "siret": "80837014200024",
    "lng": "4.19189549858968",
    "lat": "43.5679286397366"
  },
  {
    "finess": "300003993",
    "raison_sociale": "PHARMACIE DES SABLES",
    "numero voie": "91",
    "type_voie": "CHE",
    "libelle_voie": "DU MAS D AVON",
    "bp": "",
    "cp": "30220",
    "VILLE": "AIGUES MORTES",
    "tel": "466538309",
    "telecopie": "466536297",
    "categorie etablissement": "620",
    "libelle categorie": "Pharmacie d'Officine",
    "siret": "49185082200017",
    "lng": "4.19962115382937",
    "lat": "43.5685040537201"
  },
  {
    "finess": "300004447",
    "raison_sociale": "SELARL PHARMACIE DU SOLEIL",
    "numero voie": "15",
    "type_voie": "AV",
    "libelle_voie": "DE LA LIBERTE",
    "bp": "",
    "cp": "30220",
    "VILLE": "AIGUES MORTES",
    "tel": "466536130",
    "telecopie": "466538803",
    "categorie etablissement": "620",
    "libelle categorie": "Pharmacie d'Officine",
    "siret": "53094040200015",
    "lng": "4.19391611282603",
    "lat": "43.5685093393775"
  },
  {
    "finess": "300012366",
    "raison_sociale": "EHPAD COTE CANAL",
    "numero voie": "116",
    "type_voie": "R",
    "libelle_voie": "JACQUES COEUR",
    "bp": "",
    "cp": "30220",
    "VILLE": "AIGUES MORTES",
    "tel": "466800606",
    "telecopie": "466882472",
    "categorie etablissement": "500",
    "libelle categorie": "Etablissement d'hébergement pour personnes âgées dépendantes",
    "siret": "44456253200135",
    "lng": "4.18427650512841",
    "lat": "43.5740157798292"
  },
  {
    "finess": "300013398",
    "raison_sociale": "INOVIE LABOSUD AIGUES MORTES",
    "numero voie": "15",
    "type_voie": "AV",
    "libelle_voie": "FREDERIC MISTRAL",
    "bp": "",
    "cp": "30220",
    "VILLE": "AIGUES MORTES",
    "tel": "466538040",
    "telecopie": "466538445",
    "categorie etablissement": "611",
    "libelle categorie": "Laboratoire de Biologie Médicale",
    "siret": "32920877100090",
    "lng": "4.19842398323707",
    "lat": "43.5676525192325"
  },
  {
    "finess": "300018967",
    "raison_sociale": "SAAD BIEN VIVRE",
    "numero voie": "287",
    "type_voie": "R",
    "libelle_voie": "ANDRE CHAMSON",
    "bp": "",
    "cp": "30220",
    "VILLE": "AIGUES MORTES",
    "tel": "682675013",
    "telecopie": "",
    "categorie etablissement": "460",
    "libelle categorie": "Service d'Aide et d'Accompagnement à Domicile (S.A.A.D.)",
    "siret": "53304794000010",
    "lng": "4.18072890245219",
    "lat": "43.5754392757749"
  },
  {
    "finess": "300019221",
    "raison_sociale": "SESSAD VILLA B.PEYRON AIGUES MORTES",
    "numero voie": "31",
    "type_voie": "BD",
    "libelle_voie": "GAMBETTA",
    "bp": "",
    "cp": "30220",
    "VILLE": "AIGUES MORTES",
    "tel": "466049940",
    "telecopie": "",
    "categorie etablissement": "182",
    "libelle categorie": "Service d'Éducation Spéciale et de Soins à Domicile",
    "siret": "",
    "lng": "4.19203788942127",
    "lat": "43.5652500363389"
  },
  {
    "finess": "300021268",
    "raison_sociale": "SAAD AIDE A DOMICILE LANGUEDOCIENNE",
    "numero voie": "11",
    "type_voie": "AV",
    "libelle_voie": "DE LA LIBERTE",
    "bp": "",
    "cp": "30220",
    "VILLE": "AIGUES MORTES",
    "tel": "466517959",
    "telecopie": "",
    "categorie etablissement": "460",
    "libelle categorie": "Service d'Aide et d'Accompagnement à Domicile (S.A.A.D.)",
    "siret": "50266272900032",
    "lng": "4.19350807052675",
    "lat": "43.5685858127291"
  }
]