[
  {
    "finess": "190000299",
    "raison_sociale": "EHPAD ARGENTAT",
    "numero voie": "14",
    "type_voie": "AV",
    "libelle_voie": "RAYMOND POINCARE",
    "bp": "",
    "cp": "19400",
    "VILLE": "ARGENTAT SUR DORDOGNE    ",
    "tel": "555281893",
    "telecopie": "555288578",
    "categorie etablissement": "500",
    "libelle categorie": "Etablissement d'hébergement pour personnes âgées dépendantes",
    "siret": "26190100300010",
    "lng": "1.94450957562913",
    "lat": "45.091347279097"
  },
  {
    "finess": "190002618",
    "raison_sociale": "CENTRE DE SOINS INFIRMIERS",
    "numero voie": "7",
    "type_voie": "R",
    "libelle_voie": "EMMANUEL BERL",
    "bp": "",
    "cp": "19400",
    "VILLE": "ARGENTAT SUR DORDOGNE    ",
    "tel": "519640307",
    "telecopie": "",
    "categorie etablissement": "124",
    "libelle categorie": "Centre de Santé",
    "siret": "",
    "lng": "1.93546458490309",
    "lat": "45.0974340476767"
  },
  {
    "finess": "190006148",
    "raison_sociale": "ESAT ATELIERS DE CROISY",
    "numero voie": "",
    "type_voie": "RTE",
    "libelle_voie": "DU CHASTANG",
    "bp": "",
    "cp": "19400",
    "VILLE": "ARGENTAT SUR DORDOGNE    ",
    "tel": "555289123",
    "telecopie": "555283517",
    "categorie etablissement": "246",
    "libelle categorie": "Etablissement et Service d'Aide par le Travail (E.S.A.T.)",
    "siret": "77796706800126",
    "lng": "1.94441685692379",
    "lat": "45.0930942271761"
  },
  {
    "finess": "190007021",
    "raison_sociale": "PHARMACIE FARGES-CAZE",
    "numero voie": "2",
    "type_voie": "AV",
    "libelle_voie": "PASTEUR",
    "bp": "",
    "cp": "19400",
    "VILLE": "ARGENTAT SUR DORDOGNE    ",
    "tel": "555280010",
    "telecopie": "555289300",
    "categorie etablissement": "620",
    "libelle categorie": "Pharmacie d'Officine",
    "siret": "44085682100010",
    "lng": "1.93500584429227",
    "lat": "45.0932163236815"
  },
  {
    "finess": "190007054",
    "raison_sociale": "PHARMACIE CENTRALE D'ARGENTAT",
    "numero voie": "3",
    "type_voie": "AV",
    "libelle_voie": "HENRI IV",
    "bp": "",
    "cp": "19400",
    "VILLE": "ARGENTAT SUR DORDOGNE    ",
    "tel": "555281612",
    "telecopie": "",
    "categorie etablissement": "620",
    "libelle categorie": "Pharmacie d'Officine",
    "siret": "38491932000018",
    "lng": "1.9384225907782",
    "lat": "45.0936415235264"
  },
  {
    "finess": "190007070",
    "raison_sociale": "PHARMACIE BRIANCON",
    "numero voie": "8",
    "type_voie": "AV",
    "libelle_voie": "DES XAINTRIES",
    "bp": "",
    "cp": "19400",
    "VILLE": "ARGENTAT SUR DORDOGNE    ",
    "tel": "",
    "telecopie": "",
    "categorie etablissement": "620",
    "libelle categorie": "Pharmacie d'Officine",
    "siret": "35257432100027",
    "lng": "1.94035084967357",
    "lat": "45.09077113766"
  },
  {
    "finess": "190007104",
    "raison_sociale": "PHARMACIE LABROUE",
    "numero voie": "18",
    "type_voie": "AV",
    "libelle_voie": "FOCH",
    "bp": "",
    "cp": "19400",
    "VILLE": "ARGENTAT SUR DORDOGNE    ",
    "tel": "",
    "telecopie": "",
    "categorie etablissement": "620",
    "libelle categorie": "Pharmacie d'Officine",
    "siret": "30469402900048",
    "lng": "1.93264443171672",
    "lat": "45.0933171033101"
  },
  {
    "finess": "190011932",
    "raison_sociale": "LBM SYNLAB NOUVELLE-AQUITAINE - ARGENT",
    "numero voie": "",
    "type_voie": "AV",
    "libelle_voie": "JOSEPH VACHAL",
    "bp": "",
    "cp": "19400",
    "VILLE": "ARGENTAT SUR DORDOGNE    ",
    "tel": "555288166",
    "telecopie": "555281901",
    "categorie etablissement": "611",
    "libelle categorie": "Laboratoire de Biologie Médicale",
    "siret": "39393230600383",
    "lng": "1.93878346322188",
    "lat": "45.0962635513899"
  },
  {
    "finess": "190011981",
    "raison_sociale": "CMPP ARGENTAT",
    "numero voie": "",
    "type_voie": "R",
    "libelle_voie": "DE L'HOSPICE",
    "bp": "",
    "cp": "19400",
    "VILLE": "ARGENTAT SUR DORDOGNE    ",
    "tel": "555280228",
    "telecopie": "",
    "categorie etablissement": "189",
    "libelle categorie": "Centre Médico-Psycho-Pédagogique (C.M.P.P.)",
    "siret": "77796706800068",
    "lng": "1.94172820999428",
    "lat": "45.0913425188973"
  },
  {
    "finess": "190013466",
    "raison_sociale": "MSP DU PAYS D'ARGENTAT",
    "numero voie": "7",
    "type_voie": "R",
    "libelle_voie": "EMMANUEL BERL",
    "bp": "",
    "cp": "19320",
    "VILLE": "ARGENTAT SUR DORDOGNE    ",
    "tel": "686795655",
    "telecopie": "555286074",
    "categorie etablissement": "603",
    "libelle categorie": "Maison de santé (L.6223-3)",
    "siret": "83834700300025",
    "lng": "1.93546458490309",
    "lat": "45.0974340476767"
  }
]