[
  {
    "finess": "140000530",
    "raison_sociale": "ITEP CHAMP-GOUBERT",
    "numero voie": "5",
    "type_voie": "R",
    "libelle_voie": "DES FRÈRES WILKIN",
    "bp": "",
    "cp": "14460",
    "VILLE": "COLOMBELLES ",
    "tel": "231805106",
    "telecopie": "231082152",
    "categorie etablissement": "186",
    "libelle categorie": "Institut Thérapeutique Éducatif et Pédagogique (I.T.E.P.)",
    "siret": "77556139200041",
    "lng": "-0.297477274068827",
    "lat": "49.2046209012627"
  },
  {
    "finess": "140001066",
    "raison_sociale": "EHPAD \"BELLE COLOMBE\" - COLOMBELLES",
    "numero voie": "1",
    "type_voie": "R",
    "libelle_voie": "VICTOR HUGO",
    "bp": "",
    "cp": "14460",
    "VILLE": "COLOMBELLES ",
    "tel": "231358787",
    "telecopie": "231358788",
    "categorie etablissement": "500",
    "libelle categorie": "Etablissement d'hébergement pour personnes âgées dépendantes",
    "siret": "79499427700372",
    "lng": "-0.293187012547419",
    "lat": "49.2066224745405"
  },
  {
    "finess": "140007956",
    "raison_sociale": "RESIDENCE J. GOUESLARD",
    "numero voie": "",
    "type_voie": "R",
    "libelle_voie": "LUCIEN MANGEMATIN",
    "bp": "",
    "cp": "14460",
    "VILLE": "COLOMBELLES ",
    "tel": "231375700",
    "telecopie": "",
    "categorie etablissement": "202",
    "libelle categorie": "Résidences autonomie",
    "siret": "26140017000013",
    "lng": "-0.298312271070555",
    "lat": "49.2024259015666"
  },
  {
    "finess": "140009820",
    "raison_sociale": "PHARMACIE DE LA MAIRIE DE COLOMBELLES",
    "numero voie": "3",
    "type_voie": "AV",
    "libelle_voie": "DE LA LIBERTE",
    "bp": "",
    "cp": "14460",
    "VILLE": "COLOMBELLES ",
    "tel": "231724013",
    "telecopie": "231725311",
    "categorie etablissement": "620",
    "libelle categorie": "Pharmacie d'Officine",
    "siret": "88291191000017",
    "lng": "-0.296697924229174",
    "lat": "49.2038342103855"
  },
  {
    "finess": "140009838",
    "raison_sociale": "SELARL PHARMACIE VEREECKE",
    "numero voie": "49",
    "type_voie": "AV",
    "libelle_voie": "DE LA LIBERTE",
    "bp": "",
    "cp": "14460",
    "VILLE": "COLOMBELLES ",
    "tel": "231724007",
    "telecopie": "231725724",
    "categorie etablissement": "620",
    "libelle categorie": "Pharmacie d'Officine",
    "siret": "40907011700026",
    "lng": "-0.293379148805724",
    "lat": "49.2007126996475"
  },
  {
    "finess": "140016569",
    "raison_sociale": "ESAT \"APAEI DE CAEN\" - SITE SECONDAIRE",
    "numero voie": "",
    "type_voie": "R",
    "libelle_voie": "DE L'EUROPE",
    "bp": "",
    "cp": "14460",
    "VILLE": "COLOMBELLES ",
    "tel": "231521705",
    "telecopie": "231525071",
    "categorie etablissement": "246",
    "libelle categorie": "Etablissement et Service d'Aide par le Travail (E.S.A.T.)",
    "siret": "77556144200200",
    "lng": "-0.292038447395121",
    "lat": "49.193974684863"
  },
  {
    "finess": "140018458",
    "raison_sociale": "CMP COLOMBELLES (14I02)- EPSM CAEN",
    "numero voie": "6",
    "type_voie": "R",
    "libelle_voie": "ELSA TRIOLET",
    "bp": "",
    "cp": "14460",
    "VILLE": "COLOMBELLES ",
    "tel": "231525200",
    "telecopie": "",
    "categorie etablissement": "156",
    "libelle categorie": "Centre Médico-Psychologique (C.M.P.)",
    "siret": "26140127700379",
    "lng": "-0.296646856307418",
    "lat": "49.2052087120745"
  },
  {
    "finess": "140019860",
    "raison_sociale": "CENTRE MEDICO SOCIAL - COLOMBELLES",
    "numero voie": "5",
    "type_voie": "R",
    "libelle_voie": "JULES GUESDE",
    "bp": "BP 15",
    "cp": "14460",
    "VILLE": "COLOMBELLES ",
    "tel": "231351551",
    "telecopie": "",
    "categorie etablissement": "230",
    "libelle categorie": "Etablissement Consultation Protection Infantile",
    "siret": "",
    "lng": "-0.301496027714654",
    "lat": "49.2044586166993"
  },
  {
    "finess": "140023235",
    "raison_sociale": "SESSAD DE L'APAEI DE CAEN",
    "numero voie": "8",
    "type_voie": "R",
    "libelle_voie": "DE L'AVENIR",
    "bp": "",
    "cp": "14460",
    "VILLE": "COLOMBELLES ",
    "tel": "231862700",
    "telecopie": "231291310",
    "categorie etablissement": "182",
    "libelle categorie": "Service d'Éducation Spéciale et de Soins à Domicile",
    "siret": "77556144200150",
    "lng": "-0.292203631263732",
    "lat": "49.1973030719198"
  },
  {
    "finess": "140026352",
    "raison_sociale": "MAISON RELAIS ASS REVIVRE COLOMBELLES",
    "numero voie": "9",
    "type_voie": "CHE",
    "libelle_voie": "DE MONDEVILLE À GIBERVILLE",
    "bp": "",
    "cp": "14460",
    "VILLE": "COLOMBELLES ",
    "tel": "231350515",
    "telecopie": "231522978",
    "categorie etablissement": "258",
    "libelle categorie": "Maisons Relais - Pensions de Famille",
    "siret": "30772177900139",
    "lng": "-0.305843890232923",
    "lat": "49.1847421872885"
  },
  {
    "finess": "140028986",
    "raison_sociale": "POLYCLINIQUE DU PARC - PUI COLOMBELLES",
    "numero voie": "",
    "type_voie": "AV",
    "libelle_voie": "DU PAYS DE CAEN",
    "bp": "ZI NORMANDIAL",
    "cp": "14460",
    "VILLE": "COLOMBELLES ",
    "tel": "",
    "telecopie": "",
    "categorie etablissement": "699",
    "libelle categorie": "Entité Ayant Autorisation",
    "siret": "",
    "lng": "-0.298586906593468",
    "lat": "49.1971085941179"
  },
  {
    "finess": "140029257",
    "raison_sociale": "SAP COLOMBELLES DIP ACSEA",
    "numero voie": "",
    "type_voie": "PL",
    "libelle_voie": "DES TILLEULS",
    "bp": "",
    "cp": "14460",
    "VILLE": "COLOMBELLES ",
    "tel": "231343031",
    "telecopie": "231344918",
    "categorie etablissement": "286",
    "libelle categorie": "Club Equipe de Prévention",
    "siret": "77556139200694",
    "lng": "-0.30949500033963",
    "lat": "49.1842432496913"
  },
  {
    "finess": "140031139",
    "raison_sociale": "RHVS HOTELS LIBERA COLOMBELLES",
    "numero voie": "42",
    "type_voie": "R",
    "libelle_voie": "NELSON MANDELA",
    "bp": "ZAC DU LIBERA",
    "cp": "14460",
    "VILLE": "COLOMBELLES ",
    "tel": "231727878",
    "telecopie": "",
    "categorie etablissement": "216",
    "libelle categorie": "Résidence Hôtelière à Vocation Sociale (R.H.V.S.)",
    "siret": "79822684100020",
    "lng": "-0.300260530493415",
    "lat": "49.1884784715635"
  },
  {
    "finess": "140032202",
    "raison_sociale": "LAM ASSOCIATION REVIVRE",
    "numero voie": "",
    "type_voie": "CHE",
    "libelle_voie": "DE MONDEVILLE",
    "bp": "",
    "cp": "14460",
    "VILLE": "COLOMBELLES ",
    "tel": "231350515",
    "telecopie": "",
    "categorie etablissement": "213",
    "libelle categorie": "Lits d'Accueil Médicalisés (L.A.M.)",
    "siret": "",
    "lng": "-0.297216171929905",
    "lat": "49.203907304684"
  },
  {
    "finess": "140033523",
    "raison_sociale": "ACT UN CHEZ-SOI D'ABORD - CU CAEN",
    "numero voie": "9",
    "type_voie": "CHE",
    "libelle_voie": "DE MONDEVILLE",
    "bp": "",
    "cp": "14460",
    "VILLE": "COLOMBELLES ",
    "tel": "231350515",
    "telecopie": "",
    "categorie etablissement": "165",
    "libelle categorie": "Appartement de Coordination Thérapeutique (A.C.T.)",
    "siret": "",
    "lng": "-0.297216171929905",
    "lat": "49.203907304684"
  }
]