[
  {
    "finess": "560000366",
    "raison_sociale": "CENTRE HOSPITALIER GUEMENE SUR SCORFF",
    "numero voie": "",
    "type_voie": "R",
    "libelle_voie": "EMILE MAZE",
    "bp": "",
    "cp": "56160",
    "VILLE": "GUEMENE SUR SCORFF    ",
    "tel": "297285151",
    "telecopie": "297285100",
    "categorie etablissement": "106",
    "libelle categorie": "Centre hospitalier",
    "siret": "",
    "lng": "-3.20088704788333",
    "lat": "48.0693574661374"
  },
  {
    "finess": "560004244",
    "raison_sociale": "SSIAD DE GUEMENE SUR SCORFF",
    "numero voie": "",
    "type_voie": "R",
    "libelle_voie": "EMILE MAZE",
    "bp": "BP 83",
    "cp": "56160",
    "VILLE": "GUEMENE SUR SCORFF    ",
    "tel": "297285151",
    "telecopie": "297285100",
    "categorie etablissement": "354",
    "libelle categorie": "Service de Soins Infirmiers A Domicile (S.S.I.A.D)",
    "siret": "26560017100028",
    "lng": "-3.20088704788333",
    "lat": "48.0693574661374"
  },
  {
    "finess": "560004913",
    "raison_sociale": "RESIDENCE CLAIR LOGIS",
    "numero voie": "",
    "type_voie": "R",
    "libelle_voie": "EMILE MAZE",
    "bp": "",
    "cp": "56160",
    "VILLE": "GUEMENE SUR SCORFF    ",
    "tel": "297393633",
    "telecopie": "297399987",
    "categorie etablissement": "202",
    "libelle categorie": "Résidences autonomie",
    "siret": "26560119500026",
    "lng": "-3.20088704788333",
    "lat": "48.0693574661374"
  },
  {
    "finess": "560005613",
    "raison_sociale": "MAISON DE RETRAITE",
    "numero voie": "",
    "type_voie": "R",
    "libelle_voie": "EMILE MAZE",
    "bp": "BP 83",
    "cp": "56160",
    "VILLE": "GUEMENE SUR SCORFF    ",
    "tel": "297285151",
    "telecopie": "297285661",
    "categorie etablissement": "500",
    "libelle categorie": "Etablissement d'hébergement pour personnes âgées dépendantes",
    "siret": "26560017100036",
    "lng": "-3.20088704788333",
    "lat": "48.0693574661374"
  },
  {
    "finess": "560006439",
    "raison_sociale": "MAS LES BRUYERES",
    "numero voie": "",
    "type_voie": "R",
    "libelle_voie": "EMILE MAZE",
    "bp": "BP 83",
    "cp": "56160",
    "VILLE": "GUEMENE SUR SCORFF    ",
    "tel": "297285152",
    "telecopie": "297285647",
    "categorie etablissement": "255",
    "libelle categorie": "Maison d'Accueil Spécialisée (M.A.S.)",
    "siret": "26560205200010",
    "lng": "-3.20088704788333",
    "lat": "48.0693574661374"
  },
  {
    "finess": "560012734",
    "raison_sociale": "SAAD CCAS GUEMENE SUR SCORFF",
    "numero voie": "",
    "type_voie": "PL",
    "libelle_voie": "DU CHATEAU",
    "bp": "",
    "cp": "56160",
    "VILLE": "GUEMENE SUR SCORFF    ",
    "tel": "297512023",
    "telecopie": "",
    "categorie etablissement": "460",
    "libelle categorie": "Service d'Aide et d'Accompagnement à Domicile (S.A.A.D.)",
    "siret": "26560119500034",
    "lng": "-3.20787260890354",
    "lat": "48.0672827958887"
  },
  {
    "finess": "560016875",
    "raison_sociale": "SELARL PHARMACIE DE GUEMENE",
    "numero voie": "",
    "type_voie": "R",
    "libelle_voie": "JEAN LE GUENNEC",
    "bp": "",
    "cp": "56160",
    "VILLE": "GUEMENE SUR SCORFF    ",
    "tel": "297512007",
    "telecopie": "297512828",
    "categorie etablissement": "620",
    "libelle categorie": "Pharmacie d'Officine",
    "siret": "49021592800022",
    "lng": "-3.20487289742655",
    "lat": "48.0620504756386"
  },
  {
    "finess": "560022840",
    "raison_sociale": "CDS INFIRMIER ADMR DE GUEMENE/SCORFF",
    "numero voie": "22",
    "type_voie": "R",
    "libelle_voie": "BISSON",
    "bp": "",
    "cp": "56160",
    "VILLE": "GUEMENE SUR SCORFF    ",
    "tel": "297512051",
    "telecopie": "297393708",
    "categorie etablissement": "124",
    "libelle categorie": "Centre de Santé",
    "siret": "42226613000026",
    "lng": "-3.20516401937859",
    "lat": "48.0681280561736"
  },
  {
    "finess": "560024820",
    "raison_sociale": "CMPP GUEMENE SUR SCORFF",
    "numero voie": "9",
    "type_voie": "R",
    "libelle_voie": "DE BELLEVUE",
    "bp": "",
    "cp": "56160",
    "VILLE": "GUEMENE SUR SCORFF    ",
    "tel": "297382667",
    "telecopie": "",
    "categorie etablissement": "189",
    "libelle categorie": "Centre Médico-Psycho-Pédagogique (C.M.P.P.)",
    "siret": "",
    "lng": "-3.20665144344847",
    "lat": "48.0647755946197"
  },
  {
    "finess": "560026429",
    "raison_sociale": "PSP MSP DE GUEMENE",
    "numero voie": "12",
    "type_voie": "R",
    "libelle_voie": "GENERAL BRENOT",
    "bp": "",
    "cp": "56160",
    "VILLE": "GUEMENE SUR SCORFF    ",
    "tel": "297512063",
    "telecopie": "",
    "categorie etablissement": "603",
    "libelle categorie": "Maison de santé (L.6223-3)",
    "siret": "",
    "lng": "-3.20555221000338",
    "lat": "48.0669846605402"
  }
]