[
  {
    "finess": "620004408",
    "raison_sociale": "ASSOCIATION ASSAD HERMIES-MARQUION",
    "numero voie": "2",
    "type_voie": "R",
    "libelle_voie": "DU CENTRE",
    "bp": "",
    "cp": "62147",
    "VILLE": "HERMIES ",
    "tel": "321246388",
    "telecopie": "321246388",
    "categorie etablissement": "460",
    "libelle categorie": "Service d'Aide et d'Accompagnement à Domicile (S.A.A.D.)",
    "siret": "31639365100021",
    "lng": "3.04132967189314",
    "lat": "50.1120039755037"
  },
  {
    "finess": "620012161",
    "raison_sociale": "PHARMACIE CORBIER SYLVIE",
    "numero voie": "11",
    "type_voie": "",
    "libelle_voie": "GRAND PLACE",
    "bp": "",
    "cp": "62147",
    "VILLE": "HERMIES ",
    "tel": "321074100",
    "telecopie": "",
    "categorie etablissement": "620",
    "libelle categorie": "Pharmacie d'Officine",
    "siret": "50079823600013",
    "lng": "3.037611243404",
    "lat": "50.1109283744662"
  },
  {
    "finess": "620017889",
    "raison_sociale": "MARPA D'HERMIES",
    "numero voie": "10",
    "type_voie": "R",
    "libelle_voie": "DE RUYAULCOURT",
    "bp": "",
    "cp": "62147",
    "VILLE": "HERMIES ",
    "tel": "321153153",
    "telecopie": "821071923",
    "categorie etablissement": "202",
    "libelle categorie": "Résidences autonomie",
    "siret": "49455399300010",
    "lng": "3.03613027822198",
    "lat": "50.1080558581759"
  },
  {
    "finess": "620107102",
    "raison_sociale": "FOYER POUR ADULTES HANDICAPES",
    "numero voie": "41",
    "type_voie": "R",
    "libelle_voie": "D'HAVRINCOURT",
    "bp": "",
    "cp": "62147",
    "VILLE": "HERMIES ",
    "tel": "321074333",
    "telecopie": "321726678",
    "categorie etablissement": "252",
    "libelle categorie": "Foyer Hébergement Adultes Handicapés",
    "siret": "77562993400420",
    "lng": "3.04626408925698",
    "lat": "50.1108939863439"
  },
  {
    "finess": "620118216",
    "raison_sociale": "SAJ HENRIETTE DEBAY",
    "numero voie": "41",
    "type_voie": "R",
    "libelle_voie": "D'HAVRINCOURT",
    "bp": "",
    "cp": "62147",
    "VILLE": "HERMIES ",
    "tel": "321074333",
    "telecopie": "321077878",
    "categorie etablissement": "382",
    "libelle categorie": "Foyer de Vie pour Adultes Handicapés",
    "siret": "77562993400602",
    "lng": "3.04626408925698",
    "lat": "50.1108939863439"
  }
]