[
  {
    "finess": "560006876",
    "raison_sociale": "RESIDENCE PEN ER PRAT",
    "numero voie": "11",
    "type_voie": "R",
    "libelle_voie": "FRANCOISE DOLTO",
    "bp": "",
    "cp": "56650",
    "VILLE": "INZINZAC LOCHRIST",
    "tel": "297369012",
    "telecopie": "297368369",
    "categorie etablissement": "500",
    "libelle categorie": "Etablissement d'hébergement pour personnes âgées dépendantes",
    "siret": "26560070000024",
    "lng": "-3.26621029521488",
    "lat": "47.8435327089282"
  },
  {
    "finess": "560012841",
    "raison_sociale": "SAAD CCAS INZINZAC LOCHRIST",
    "numero voie": "",
    "type_voie": "PL",
    "libelle_voie": "CHARLES DE GAULLE",
    "bp": "BP 12",
    "cp": "56650",
    "VILLE": "INZINZAC LOCHRIST",
    "tel": "297853033",
    "telecopie": "297853040",
    "categorie etablissement": "460",
    "libelle categorie": "Service d'Aide et d'Accompagnement à Domicile (S.A.A.D.)",
    "siret": "26560070000032",
    "lng": "-3.26670482725125",
    "lat": "47.8436660353828"
  },
  {
    "finess": "560017360",
    "raison_sociale": "PHARMACIE DE TREMELIN",
    "numero voie": "",
    "type_voie": "R",
    "libelle_voie": "des Anciens Combattants",
    "bp": "ZA de Pen Ar Prat",
    "cp": "56650",
    "VILLE": "INZINZAC LOCHRIST",
    "tel": "",
    "telecopie": "",
    "categorie etablissement": "620",
    "libelle categorie": "Pharmacie d'Officine",
    "siret": "43422557900011",
    "lng": "-3.26507377062455",
    "lat": "47.8391786715967"
  },
  {
    "finess": "560017394",
    "raison_sociale": "SELARL PHARMACIE DES FORGES",
    "numero voie": "6",
    "type_voie": "QUA",
    "libelle_voie": "JULIEN LE GRAND",
    "bp": "",
    "cp": "56650",
    "VILLE": "INZINZAC LOCHRIST",
    "tel": "297360473",
    "telecopie": "970625206",
    "categorie etablissement": "620",
    "libelle categorie": "Pharmacie d'Officine",
    "siret": "39240653400025",
    "lng": "-3.24868580791708",
    "lat": "47.8264879763624"
  }
]