[
  {
    "finess": "560005316",
    "raison_sociale": "HOP DE JOUR CMP CATTP PORT LOUIS",
    "numero voie": "",
    "type_voie": "RTE",
    "libelle_voie": "DE LA CITADELLE",
    "bp": "",
    "cp": "56290",
    "VILLE": "PORT LOUIS",
    "tel": "297821387",
    "telecopie": "",
    "categorie etablissement": "292",
    "libelle categorie": "Centre Hospitalier Spécialisé lutte Maladies Mentales",
    "siret": "26560026200058",
    "lng": "-3.35394415289196",
    "lat": "47.706472896893"
  },
  {
    "finess": "560020364",
    "raison_sociale": "SELARL PHARMACIE DE PORT-LOUIS",
    "numero voie": "8",
    "type_voie": "",
    "libelle_voie": "GRANDE RUE",
    "bp": "",
    "cp": "56290",
    "VILLE": "PORT LOUIS",
    "tel": "",
    "telecopie": "",
    "categorie etablissement": "620",
    "libelle categorie": "Pharmacie d'Officine",
    "siret": "35230698900018",
    "lng": "-3.35370838930083",
    "lat": "47.7077020528185"
  },
  {
    "finess": "970102372",
    "raison_sociale": "CLASS DE PORT LOUIS",
    "numero voie": "",
    "type_voie": "R",
    "libelle_voie": "GAMBETTA",
    "bp": "",
    "cp": "97117",
    "VILLE": "PORT LOUIS",
    "tel": "590849062",
    "telecopie": "590932427",
    "categorie etablissement": "223",
    "libelle categorie": "Protection Maternelle et Infantile (P.M.I.)",
    "siret": "22971001700059",
    "lng": "2.68583310006105",
    "lat": "6.42236102878452"
  },
  {
    "finess": "970105060",
    "raison_sociale": "SERVICE LONGAN",
    "numero voie": "1",
    "type_voie": "R",
    "libelle_voie": "ALBERT BEVILLE",
    "bp": "",
    "cp": "97117",
    "VILLE": "PORT LOUIS",
    "tel": "590229636",
    "telecopie": "590287672",
    "categorie etablissement": "354",
    "libelle categorie": "Service de Soins Infirmiers A Domicile (S.S.I.A.D)",
    "siret": "33230348600028",
    "lng": "2.68617324591506",
    "lat": "6.42401941525541"
  },
  {
    "finess": "970107017",
    "raison_sociale": "PHARMACIE DE PORT-LOUIS",
    "numero voie": "43",
    "type_voie": "R",
    "libelle_voie": "GAMBETTA",
    "bp": "",
    "cp": "97117",
    "VILLE": "PORT LOUIS",
    "tel": "",
    "telecopie": "",
    "categorie etablissement": "620",
    "libelle categorie": "Pharmacie d'Officine",
    "siret": "81403931900011",
    "lng": "2.68555857755346",
    "lat": "6.42233661793011"
  },
  {
    "finess": "970109302",
    "raison_sociale": "E.H.P.A.D. SOLEYANOU",
    "numero voie": "",
    "type_voie": "ZAC",
    "libelle_voie": "DE RODRIGUE",
    "bp": "",
    "cp": "97117",
    "VILLE": "PORT LOUIS",
    "tel": "590472711",
    "telecopie": "590473602",
    "categorie etablissement": "500",
    "libelle categorie": "Etablissement d'hébergement pour personnes âgées dépendantes",
    "siret": "49072621300047",
    "lng": "2.68883194234357",
    "lat": "6.42535034186129"
  },
  {
    "finess": "970110151",
    "raison_sociale": "S.E.S.S.A.D. DENIS FORESTIER",
    "numero voie": "",
    "type_voie": "RTE",
    "libelle_voie": "DU CHATEAU",
    "bp": "HAUT DE LA  MONTAGNE",
    "cp": "97117",
    "VILLE": "PORT LOUIS",
    "tel": "590987235",
    "telecopie": "590988297",
    "categorie etablissement": "182",
    "libelle categorie": "Service d'Éducation Spéciale et de Soins à Domicile",
    "siret": "",
    "lng": "2.68464003516394",
    "lat": "6.42251585240873"
  },
  {
    "finess": "970112678",
    "raison_sociale": "MAISON DE SANTE DU NORD GRANDE-TERRE",
    "numero voie": "",
    "type_voie": "",
    "libelle_voie": "",
    "bp": "BEAUPLAN",
    "cp": "97117",
    "VILLE": "PORT LOUIS",
    "tel": "",
    "telecopie": "",
    "categorie etablissement": "603",
    "libelle categorie": "Maison de santé (L.6223-3)",
    "siret": "",
    "lng": "2.73183116226727",
    "lat": "6.42374250362995"
  },
  {
    "finess": "970112991",
    "raison_sociale": "LE SOUFFLE DU NORD",
    "numero voie": "",
    "type_voie": "R",
    "libelle_voie": "GUY MERAULT",
    "bp": "",
    "cp": "97117",
    "VILLE": "PORT LOUIS",
    "tel": "",
    "telecopie": "",
    "categorie etablissement": "603",
    "libelle categorie": "Maison de santé (L.6223-3)",
    "siret": "84409319500015",
    "lng": "2.68999209067645",
    "lat": "6.42189800188732"
  },
  {
    "finess": "970114559",
    "raison_sociale": "S. I. P. S.",
    "numero voie": "33",
    "type_voie": "R",
    "libelle_voie": "CHARLES CAIGNET",
    "bp": "",
    "cp": "97117",
    "VILLE": "PORT LOUIS",
    "tel": "590480403",
    "telecopie": "",
    "categorie etablissement": "460",
    "libelle categorie": "Service d'Aide et d'Accompagnement à Domicile (S.A.A.D.)",
    "siret": "51230754700012",
    "lng": "2.686144418387",
    "lat": "6.42302463986938"
  },
  {
    "finess": "970114690",
    "raison_sociale": "VIE ET JEUNESSE",
    "numero voie": "",
    "type_voie": "",
    "libelle_voie": "",
    "bp": "SECTION GOGUETTE",
    "cp": "97117",
    "VILLE": "PORT LOUIS",
    "tel": "590682062",
    "telecopie": "",
    "categorie etablissement": "460",
    "libelle categorie": "Service d'Aide et d'Accompagnement à Domicile (S.A.A.D.)",
    "siret": "44830319800015",
    "lng": "2.69762621412725",
    "lat": "6.44563955736103"
  },
  {
    "finess": "970114955",
    "raison_sociale": "TRANS'AIDES NORD GRANDE TERRE",
    "numero voie": "",
    "type_voie": "",
    "libelle_voie": "",
    "bp": "FAUVETTE",
    "cp": "97117",
    "VILLE": "PORT LOUIS",
    "tel": "",
    "telecopie": "",
    "categorie etablissement": "460",
    "libelle categorie": "Service d'Aide et d'Accompagnement à Domicile (S.A.A.D.)",
    "siret": "80229910700010",
    "lng": "2.69248791248248",
    "lat": "6.4289514154481"
  },
  {
    "finess": "970115085",
    "raison_sociale": "GRETA DE LA GUADELOUPE",
    "numero voie": "",
    "type_voie": "RTE",
    "libelle_voie": "DE BEAUPORT",
    "bp": "",
    "cp": "97117",
    "VILLE": "PORT LOUIS",
    "tel": "590577992",
    "telecopie": "",
    "categorie etablissement": "330",
    "libelle categorie": "Ecoles Formant aux Professions Sociales",
    "siret": "",
    "lng": "2.69536427812563",
    "lat": "6.42038215166417"
  },
  {
    "finess": "970115804",
    "raison_sociale": "CENTRE EDUCATIF FERME",
    "numero voie": "",
    "type_voie": "",
    "libelle_voie": "GOGUETTE",
    "bp": "",
    "cp": "97117",
    "VILLE": "PORT LOUIS",
    "tel": "590224052",
    "telecopie": "",
    "categorie etablissement": "241",
    "libelle categorie": "Foyer d'Action Educative (F.A.E.)",
    "siret": "77568550600906",
    "lng": "2.69762621412725",
    "lat": "6.44563955736103"
  }
]