[
  {
    "finess": "590000618",
    "raison_sociale": "CH VALENCIENNES",
    "numero voie": "114",
    "type_voie": "AV",
    "libelle_voie": "DESANDROUINS",
    "bp": "BP 479",
    "cp": "59322",
    "VILLE": "VALENCIENNES ",
    "tel": "327143333",
    "telecopie": "327143112",
    "categorie etablissement": "355",
    "libelle categorie": "Centre Hospitalier (C.H.)",
    "siret": "26590673500013",
    "lng": "3.49584003556529",
    "lat": "50.3614750523127"
  },
  {
    "finess": "590006821",
    "raison_sociale": "SESSAD APF DE VALENCIENNES",
    "numero voie": "108",
    "type_voie": "R",
    "libelle_voie": "DE FAMARS",
    "bp": "",
    "cp": "59300",
    "VILLE": "VALENCIENNES ",
    "tel": "327305270",
    "telecopie": "327305279",
    "categorie etablissement": "182",
    "libelle categorie": "Service d'Éducation Spéciale et de Soins à Domicile",
    "siret": "77568873206019",
    "lng": "3.52260180662641",
    "lat": "50.3532188981374"
  },
  {
    "finess": "590007027",
    "raison_sociale": "CATTP 59G31 & 59G32 CH VALENCIENNES",
    "numero voie": "6",
    "type_voie": "R",
    "libelle_voie": "PERCEPAIN",
    "bp": "",
    "cp": "59300",
    "VILLE": "VALENCIENNES ",
    "tel": "327200427",
    "telecopie": "327142749",
    "categorie etablissement": "425",
    "libelle categorie": "Centre d'Accueil Thérapeutique à temps partiel (C.A.T.T.P.)",
    "siret": "26590673500260",
    "lng": "3.52501220491803",
    "lat": "50.3618230711444"
  },
  {
    "finess": "590007910",
    "raison_sociale": "SCE DE PMI-114",
    "numero voie": "13",
    "type_voie": "PL",
    "libelle_voie": "VERTE",
    "bp": "BP 461",
    "cp": "59322",
    "VILLE": "VALENCIENNES ",
    "tel": "327472387",
    "telecopie": "",
    "categorie etablissement": "223",
    "libelle categorie": "Protection Maternelle et Infantile (P.M.I.)",
    "siret": "",
    "lng": "3.52895081632978",
    "lat": "50.3578415771867"
  },
  {
    "finess": "590007951",
    "raison_sociale": "SCE DE PMI-123",
    "numero voie": "57",
    "type_voie": "AV",
    "libelle_voie": "FAIDHERBE",
    "bp": "BP 431",
    "cp": "59322",
    "VILLE": "VALENCIENNES ",
    "tel": "327425200",
    "telecopie": "",
    "categorie etablissement": "223",
    "libelle categorie": "Protection Maternelle et Infantile (P.M.I.)",
    "siret": "",
    "lng": "3.50750325308199",
    "lat": "50.3549392560686"
  },
  {
    "finess": "590008041",
    "raison_sociale": "POLYCLINIQUE VAUBAN",
    "numero voie": "10",
    "type_voie": "AV",
    "libelle_voie": "VAUBAN",
    "bp": "",
    "cp": "59300",
    "VILLE": "VALENCIENNES ",
    "tel": "327324252",
    "telecopie": "327324253",
    "categorie etablissement": "365",
    "libelle categorie": "Etablissement de Soins Pluridisciplinaire",
    "siret": "41490897000026",
    "lng": "3.51228391239947",
    "lat": "50.3600217049871"
  },
  {
    "finess": "590008322",
    "raison_sociale": "CENTRE ALCOOLOGIQUE DE JOUR",
    "numero voie": "25",
    "type_voie": "R",
    "libelle_voie": "GENERAL HORNE",
    "bp": "",
    "cp": "59300",
    "VILLE": "VALENCIENNES ",
    "tel": "",
    "telecopie": "",
    "categorie etablissement": "425",
    "libelle categorie": "Centre d'Accueil Thérapeutique à temps partiel (C.A.T.T.P.)",
    "siret": "26590697400059",
    "lng": "3.52203248076484",
    "lat": "50.3506769198057"
  },
  {
    "finess": "590025128",
    "raison_sociale": "HAD DU HAINAUT",
    "numero voie": "118",
    "type_voie": "AV",
    "libelle_voie": "DESANDROUINS",
    "bp": "BP 30333",
    "cp": "59300",
    "VILLE": "VALENCIENNES ",
    "tel": "327142500",
    "telecopie": "327142501",
    "categorie etablissement": "127",
    "libelle categorie": "Hospitalisation à Domicile",
    "siret": "31245483800276",
    "lng": "3.49584003556529",
    "lat": "50.3614750523127"
  },
  {
    "finess": "590029229",
    "raison_sociale": "SCE AIDE A DOMICILE",
    "numero voie": "43",
    "type_voie": "R",
    "libelle_voie": "DE PARIS",
    "bp": "",
    "cp": "59300",
    "VILLE": "VALENCIENNES ",
    "tel": "327282340",
    "telecopie": "327282331",
    "categorie etablissement": "460",
    "libelle categorie": "Service d'Aide et d'Accompagnement à Domicile (S.A.A.D.)",
    "siret": "41046901900039",
    "lng": "3.5129112822171",
    "lat": "50.3531141077482"
  },
  {
    "finess": "590029559",
    "raison_sociale": "IRTS SITE HAINAUT CAMBRESIS",
    "numero voie": "35",
    "type_voie": "R",
    "libelle_voie": "ERNEST MACAREZ",
    "bp": "",
    "cp": "59300",
    "VILLE": "VALENCIENNES ",
    "tel": "327424097",
    "telecopie": "327424098",
    "categorie etablissement": "330",
    "libelle categorie": "Ecoles Formant aux Professions Sociales",
    "siret": "31807145300126",
    "lng": "3.53595759599094",
    "lat": "50.3723618768361"
  },
  {
    "finess": "590029849",
    "raison_sociale": "CREFO VALENCIENNES",
    "numero voie": "43",
    "type_voie": "R",
    "libelle_voie": "DE L'ABREUVOIR",
    "bp": "",
    "cp": "59300",
    "VILLE": "VALENCIENNES ",
    "tel": "327294985",
    "telecopie": "327294015",
    "categorie etablissement": "330",
    "libelle categorie": "Ecoles Formant aux Professions Sociales",
    "siret": "78371481900209",
    "lng": "3.51235097614365",
    "lat": "50.3537655484201"
  },
  {
    "finess": "590030029",
    "raison_sociale": "AEMO UDAF VALENCIENNES",
    "numero voie": "5",
    "type_voie": "R",
    "libelle_voie": "DES CENT-TÊTES",
    "bp": "",
    "cp": "59300",
    "VILLE": "VALENCIENNES ",
    "tel": "327475280",
    "telecopie": "327475281",
    "categorie etablissement": "295",
    "libelle categorie": "Services AEMO et AED",
    "siret": "78371464500521",
    "lng": "3.53032104013114",
    "lat": "50.3653771889356"
  },
  {
    "finess": "590031183",
    "raison_sociale": "PHARMACIE BARTHOLOME",
    "numero voie": "41",
    "type_voie": "R",
    "libelle_voie": "DE MONS",
    "bp": "",
    "cp": "59300",
    "VILLE": "VALENCIENNES ",
    "tel": "327463281",
    "telecopie": "327459031",
    "categorie etablissement": "620",
    "libelle categorie": "Pharmacie d'Officine",
    "siret": "51286283000019",
    "lng": "3.52862592672954",
    "lat": "50.3599195801834"
  },
  {
    "finess": "590031233",
    "raison_sociale": "PHARMACIE DU CANADA",
    "numero voie": "1",
    "type_voie": "PL",
    "libelle_voie": "DU CANADA",
    "bp": "",
    "cp": "59300",
    "VILLE": "VALENCIENNES ",
    "tel": "327463540",
    "telecopie": "",
    "categorie etablissement": "620",
    "libelle categorie": "Pharmacie d'Officine",
    "siret": "84072360500019",
    "lng": "3.52263471391047",
    "lat": "50.3528731032189"
  },
  {
    "finess": "590031266",
    "raison_sociale": "PHARMACIE OFFROY",
    "numero voie": "",
    "type_voie": "AV",
    "libelle_voie": "DU GENERAL HORNE",
    "bp": "",
    "cp": "59300",
    "VILLE": "VALENCIENNES ",
    "tel": "327466550",
    "telecopie": "327427354",
    "categorie etablissement": "620",
    "libelle categorie": "Pharmacie d'Officine",
    "siret": "38053334900011",
    "lng": "3.52104030049514",
    "lat": "50.3498479451794"
  },
  {
    "finess": "590031282",
    "raison_sociale": "PHARMACIE DE LA PYRAMIDE II",
    "numero voie": "329",
    "type_voie": "AV",
    "libelle_voie": "DAMPIERRE",
    "bp": "",
    "cp": "59300",
    "VILLE": "VALENCIENNES ",
    "tel": "327463601",
    "telecopie": "327425071",
    "categorie etablissement": "620",
    "libelle categorie": "Pharmacie d'Officine",
    "siret": "90778318700012",
    "lng": "3.50467068341489",
    "lat": "50.3573964822979"
  },
  {
    "finess": "590031316",
    "raison_sociale": "MCT PHARMA",
    "numero voie": "23",
    "type_voie": "R",
    "libelle_voie": "THOLOZE",
    "bp": "",
    "cp": "59300",
    "VILLE": "VALENCIENNES ",
    "tel": "327462043",
    "telecopie": "327462043",
    "categorie etablissement": "620",
    "libelle categorie": "Pharmacie d'Officine",
    "siret": "75372683500014",
    "lng": "3.51797488723643",
    "lat": "50.3626240079221"
  },
  {
    "finess": "590031357",
    "raison_sociale": "PHARMACIE DE LA FONTAINE",
    "numero voie": "10",
    "type_voie": "R",
    "libelle_voie": "DE PARIS",
    "bp": "",
    "cp": "59300",
    "VILLE": "VALENCIENNES ",
    "tel": "327462075",
    "telecopie": "327257879",
    "categorie etablissement": "620",
    "libelle categorie": "Pharmacie d'Officine",
    "siret": "50776959400015",
    "lng": "3.51571717214584",
    "lat": "50.3548414628679"
  },
  {
    "finess": "590031373",
    "raison_sociale": "PHARMACIE MORMENTYN",
    "numero voie": "214",
    "type_voie": "R",
    "libelle_voie": "DE LOMPREZ",
    "bp": "",
    "cp": "59300",
    "VILLE": "VALENCIENNES ",
    "tel": "327468527",
    "telecopie": "327294816",
    "categorie etablissement": "620",
    "libelle categorie": "Pharmacie d'Officine",
    "siret": "45148372100010",
    "lng": "3.48704736625948",
    "lat": "50.3534828420719"
  },
  {
    "finess": "590031423",
    "raison_sociale": "GRANDE PHARMACIE DE VALENCIENNES",
    "numero voie": "6",
    "type_voie": "PL",
    "libelle_voie": "DU MARCHE AUX HERBES",
    "bp": "",
    "cp": "59300",
    "VILLE": "VALENCIENNES ",
    "tel": "327463239",
    "telecopie": "327360193",
    "categorie etablissement": "620",
    "libelle categorie": "Pharmacie d'Officine",
    "siret": "41751434600010",
    "lng": "3.52323482498614",
    "lat": "50.3596013876233"
  },
  {
    "finess": "590031472",
    "raison_sociale": "PHARMACIE DE SAINT-WAAST",
    "numero voie": "200",
    "type_voie": "AV",
    "libelle_voie": "DESANDROUINS",
    "bp": "",
    "cp": "59300",
    "VILLE": "VALENCIENNES ",
    "tel": "327466927",
    "telecopie": "327460069",
    "categorie etablissement": "620",
    "libelle categorie": "Pharmacie d'Officine",
    "siret": "84190424600011",
    "lng": "3.49409378149929",
    "lat": "50.3623026379208"
  },
  {
    "finess": "590031522",
    "raison_sociale": "PHARMACIE DE ROMAINVILLE",
    "numero voie": "104",
    "type_voie": "AV",
    "libelle_voie": "DE VERDUN",
    "bp": "",
    "cp": "59300",
    "VILLE": "VALENCIENNES ",
    "tel": "327464103",
    "telecopie": "227464103",
    "categorie etablissement": "620",
    "libelle categorie": "Pharmacie d'Officine",
    "siret": "44873143000014",
    "lng": "3.53620246841328",
    "lat": "50.3523237993927"
  },
  {
    "finess": "590031555",
    "raison_sociale": "PHARMACIE DE L'EUROPE",
    "numero voie": "24",
    "type_voie": "AV",
    "libelle_voie": "ALBERT 1ER",
    "bp": "",
    "cp": "59300",
    "VILLE": "VALENCIENNES ",
    "tel": "327462507",
    "telecopie": "327302262",
    "categorie etablissement": "620",
    "libelle categorie": "Pharmacie d'Officine",
    "siret": "83005899600018",
    "lng": "3.52604252300363",
    "lat": "50.3587383399123"
  },
  {
    "finess": "590031829",
    "raison_sociale": "SAD HAINAUT LABEL VIE",
    "numero voie": "41",
    "type_voie": "BD",
    "libelle_voie": "WATTEAU",
    "bp": "",
    "cp": "59300",
    "VILLE": "VALENCIENNES ",
    "tel": "327264444",
    "telecopie": "",
    "categorie etablissement": "460",
    "libelle categorie": "Service d'Aide et d'Accompagnement à Domicile (S.A.A.D.)",
    "siret": "48282008100032",
    "lng": "3.53115711956617",
    "lat": "50.3559907093201"
  },
  {
    "finess": "590033296",
    "raison_sociale": "FOYER DE VIE BETHSAIDE",
    "numero voie": "11",
    "type_voie": "BD",
    "libelle_voie": "SALY",
    "bp": "",
    "cp": "59300",
    "VILLE": "VALENCIENNES ",
    "tel": "327427956",
    "telecopie": "327987836",
    "categorie etablissement": "252",
    "libelle categorie": "Foyer Hébergement Adultes Handicapés",
    "siret": "35243218100043",
    "lng": "3.52110910220917",
    "lat": "50.3531174732136"
  },
  {
    "finess": "590033338",
    "raison_sociale": "SAVS APF VALENCIENNES",
    "numero voie": "4",
    "type_voie": "R",
    "libelle_voie": "JEAN DAUBY",
    "bp": "",
    "cp": "59300",
    "VILLE": "VALENCIENNES ",
    "tel": "327469706",
    "telecopie": "327469707",
    "categorie etablissement": "446",
    "libelle categorie": "Service d'Accompagnement à la Vie Sociale (S.A.V.S.)",
    "siret": "77568873210763",
    "lng": "3.49688127813664",
    "lat": "50.3596061441149"
  },
  {
    "finess": "590033866",
    "raison_sociale": "CENTRE DU PONT NEUF",
    "numero voie": "121",
    "type_voie": "AV",
    "libelle_voie": "DAMPIERRE",
    "bp": "",
    "cp": "59300",
    "VILLE": "VALENCIENNES ",
    "tel": "327294252",
    "telecopie": "",
    "categorie etablissement": "197",
    "libelle categorie": "Centre soins accompagnement prévention addictologie (CSAPA)",
    "siret": "",
    "lng": "3.50788118084586",
    "lat": "50.3625205076602"
  },
  {
    "finess": "590035044",
    "raison_sociale": "PETITE UNITE DE VIE DESANDROUIN",
    "numero voie": "71",
    "type_voie": "AV",
    "libelle_voie": "DESANDROUIN",
    "bp": "",
    "cp": "59300",
    "VILLE": "VALENCIENNES ",
    "tel": "327296618",
    "telecopie": "327256618",
    "categorie etablissement": "500",
    "libelle categorie": "Etablissement d'hébergement pour personnes âgées dépendantes",
    "siret": "49972277500016",
    "lng": "3.49746885711043",
    "lat": "50.3605572368185"
  },
  {
    "finess": "590035051",
    "raison_sociale": "MAISON COMMUNAUTAIRE DES CANONNIERS",
    "numero voie": "9",
    "type_voie": "PL",
    "libelle_voie": "DE L'HOPITAL GENERAL",
    "bp": "",
    "cp": "59300",
    "VILLE": "VALENCIENNES ",
    "tel": "327301797",
    "telecopie": "",
    "categorie etablissement": "202",
    "libelle categorie": "Résidences autonomie",
    "siret": "49972277500024",
    "lng": "3.52559279826668",
    "lat": "50.3621842076417"
  },
  {
    "finess": "590037537",
    "raison_sociale": "EHPAD LA RHONELLE",
    "numero voie": "6",
    "type_voie": "R",
    "libelle_voie": "DAVAINE",
    "bp": "",
    "cp": "59300",
    "VILLE": "VALENCIENNES ",
    "tel": "320147680",
    "telecopie": "327143657",
    "categorie etablissement": "500",
    "libelle categorie": "Etablissement d'hébergement pour personnes âgées dépendantes",
    "siret": "26590673500393",
    "lng": "3.52329007353137",
    "lat": "50.3642571217661"
  },
  {
    "finess": "590037628",
    "raison_sociale": "CADA ADOMA NORD",
    "numero voie": "35",
    "type_voie": "R",
    "libelle_voie": "DES ANGES",
    "bp": "",
    "cp": "59300",
    "VILLE": "VALENCIENNES ",
    "tel": "327472580",
    "telecopie": "327472315",
    "categorie etablissement": "443",
    "libelle categorie": "Centre Accueil Demandeurs Asile (C.A.D.A.)",
    "siret": "78805803007763",
    "lng": "3.52001547665855",
    "lat": "50.3578409410332"
  },
  {
    "finess": "590038923",
    "raison_sociale": "CSAPA CENTRE LA BOUSSOLE",
    "numero voie": "57",
    "type_voie": "AV",
    "libelle_voie": "DÉSANDROUIN",
    "bp": "",
    "cp": "59322",
    "VILLE": "VALENCIENNES ",
    "tel": "327140590",
    "telecopie": "327140591",
    "categorie etablissement": "197",
    "libelle categorie": "Centre soins accompagnement prévention addictologie (CSAPA)",
    "siret": "",
    "lng": "3.5008636459216",
    "lat": "50.3587003313292"
  },
  {
    "finess": "590039301",
    "raison_sociale": "SAJ APF VALENCIENNES",
    "numero voie": "4",
    "type_voie": "R",
    "libelle_voie": "JEAN DAUBY",
    "bp": "",
    "cp": "59300",
    "VILLE": "VALENCIENNES ",
    "tel": "327469706",
    "telecopie": "327469707",
    "categorie etablissement": "382",
    "libelle categorie": "Foyer de Vie pour Adultes Handicapés",
    "siret": "77568873207132",
    "lng": "3.49688127813664",
    "lat": "50.3596061441149"
  },
  {
    "finess": "590039327",
    "raison_sociale": "FH APF VALENCIENNES",
    "numero voie": "4",
    "type_voie": "R",
    "libelle_voie": "JEAN DAUBY",
    "bp": "",
    "cp": "59300",
    "VILLE": "VALENCIENNES ",
    "tel": "327469706",
    "telecopie": "327469707",
    "categorie etablissement": "252",
    "libelle categorie": "Foyer Hébergement Adultes Handicapés",
    "siret": "77568873207132",
    "lng": "3.49688127813664",
    "lat": "50.3596061441149"
  },
  {
    "finess": "590040390",
    "raison_sociale": "EFS NORD DE FRANCE VALENCIENNES TERT",
    "numero voie": "",
    "type_voie": "CHE",
    "libelle_voie": "DES ALLIES",
    "bp": "",
    "cp": "59300",
    "VILLE": "VALENCIENNES ",
    "tel": "328547916",
    "telecopie": "328547920",
    "categorie etablissement": "132",
    "libelle categorie": "Etablissement de Transfusion Sanguine",
    "siret": "",
    "lng": "3.53259370698986",
    "lat": "50.3667320474424"
  },
  {
    "finess": "590043030",
    "raison_sociale": "CENTRE DE PLANIFICATION FAMILIALE",
    "numero voie": "",
    "type_voie": "R",
    "libelle_voie": "JEAN JAURES",
    "bp": "",
    "cp": "59300",
    "VILLE": "VALENCIENNES ",
    "tel": "327417432",
    "telecopie": "",
    "categorie etablissement": "228",
    "libelle categorie": "Centre Planification ou Education Familiale",
    "siret": "",
    "lng": "3.5362933686363",
    "lat": "50.3517658650551"
  },
  {
    "finess": "590044236",
    "raison_sociale": "PETITE UNITE DE VIE DES CANONNIERS",
    "numero voie": "9",
    "type_voie": "PL",
    "libelle_voie": "DE L'HOPITAL GENERAL",
    "bp": "",
    "cp": "59300",
    "VILLE": "VALENCIENNES ",
    "tel": "327301797",
    "telecopie": "327301797",
    "categorie etablissement": "500",
    "libelle categorie": "Etablissement d'hébergement pour personnes âgées dépendantes",
    "siret": "49961438600013",
    "lng": "3.52559279826668",
    "lat": "50.3621842076417"
  },
  {
    "finess": "590045423",
    "raison_sociale": "EHPAD VAL D'ESCAUT",
    "numero voie": "",
    "type_voie": "PL",
    "libelle_voie": "DE LA CONCORDE",
    "bp": "",
    "cp": "59300",
    "VILLE": "VALENCIENNES ",
    "tel": "327147680",
    "telecopie": "327147677",
    "categorie etablissement": "500",
    "libelle categorie": "Etablissement d'hébergement pour personnes âgées dépendantes",
    "siret": "",
    "lng": "3.49952210396381",
    "lat": "50.3635368023811"
  },
  {
    "finess": "590046207",
    "raison_sociale": "SERVICE D'AEMO ADNSEA VALENCIENNES",
    "numero voie": "45",
    "type_voie": "BD",
    "libelle_voie": "WATTEAU",
    "bp": "",
    "cp": "59300",
    "VILLE": "VALENCIENNES ",
    "tel": "327243880",
    "telecopie": "327243881",
    "categorie etablissement": "295",
    "libelle categorie": "Services AEMO et AED",
    "siret": "77562467900699",
    "lng": "3.5309944292812",
    "lat": "50.355732841868"
  },
  {
    "finess": "590046793",
    "raison_sociale": "EHPAD DU FAUBOURG DE LILLE",
    "numero voie": "9",
    "type_voie": "R",
    "libelle_voie": "ADRIEN DE MONTIGNY",
    "bp": "",
    "cp": "59300",
    "VILLE": "VALENCIENNES ",
    "tel": "327343122",
    "telecopie": "",
    "categorie etablissement": "500",
    "libelle categorie": "Etablissement d'hébergement pour personnes âgées dépendantes",
    "siret": "52794945700016",
    "lng": "3.51750111615536",
    "lat": "50.3704924263913"
  },
  {
    "finess": "590047536",
    "raison_sociale": "RESIDENCE SOCIALE LEONCE DE FIEUZAL",
    "numero voie": "26",
    "type_voie": "AV",
    "libelle_voie": "DES DENTELLIERES",
    "bp": "",
    "cp": "59300",
    "VILLE": "VALENCIENNES ",
    "tel": "327411794",
    "telecopie": "",
    "categorie etablissement": "259",
    "libelle categorie": "Autre Résidence Sociale (hors Maison Relais",
    "siret": "",
    "lng": "3.51817177025451",
    "lat": "50.3554111629485"
  },
  {
    "finess": "590047544",
    "raison_sociale": "RESIDENCE SOCIALE JOSEPHINE DUCHESNOIS",
    "numero voie": "22",
    "type_voie": "R",
    "libelle_voie": "DU FAUBOURG DE PARIS",
    "bp": "",
    "cp": "59300",
    "VILLE": "VALENCIENNES ",
    "tel": "327411794",
    "telecopie": "",
    "categorie etablissement": "259",
    "libelle categorie": "Autre Résidence Sociale (hors Maison Relais",
    "siret": "",
    "lng": "3.51535822397066",
    "lat": "50.3544578042668"
  },
  {
    "finess": "590047551",
    "raison_sociale": "RESIDENCE SOCIALE DESFONTAINES DEPREUX",
    "numero voie": "3",
    "type_voie": "R",
    "libelle_voie": "OULTREMAN",
    "bp": "",
    "cp": "59300",
    "VILLE": "VALENCIENNES ",
    "tel": "327411794",
    "telecopie": "",
    "categorie etablissement": "259",
    "libelle categorie": "Autre Résidence Sociale (hors Maison Relais",
    "siret": "",
    "lng": "3.52235239772876",
    "lat": "50.3559690320763"
  },
  {
    "finess": "590047569",
    "raison_sociale": "RESIDENCE SOCIALE ANDRE DUPARCQ",
    "numero voie": "103",
    "type_voie": "R",
    "libelle_voie": "DE PARIS",
    "bp": "",
    "cp": "59300",
    "VILLE": "VALENCIENNES ",
    "tel": "327411794",
    "telecopie": "",
    "categorie etablissement": "259",
    "libelle categorie": "Autre Résidence Sociale (hors Maison Relais",
    "siret": "",
    "lng": "3.51918185641632",
    "lat": "50.3581128926609"
  },
  {
    "finess": "590048161",
    "raison_sociale": "CENTRE DE PREORIENTATION ANDRE MAGINOT",
    "numero voie": "30",
    "type_voie": "R",
    "libelle_voie": "DES FRÈRES DANNA",
    "bp": "",
    "cp": "59300",
    "VILLE": "VALENCIENNES ",
    "tel": "327477500",
    "telecopie": "327241314",
    "categorie etablissement": "198",
    "libelle categorie": "Etablissement et Service de Préorientation",
    "siret": "18003606300014",
    "lng": "3.52879234137297",
    "lat": "50.3671021181187"
  },
  {
    "finess": "590048393",
    "raison_sociale": "CAARUD LE TARMAC",
    "numero voie": "50",
    "type_voie": "BD",
    "libelle_voie": "FROISSART",
    "bp": "",
    "cp": "59300",
    "VILLE": "VALENCIENNES ",
    "tel": "327285737",
    "telecopie": "",
    "categorie etablissement": "178",
    "libelle categorie": "Ctre.Accueil/ Accomp.Réduc.Risq.Usag. Drogues (C.A.A.R.U.D.)",
    "siret": "35148399500079",
    "lng": "3.52121675346827",
    "lat": "50.3631436517233"
  },
  {
    "finess": "590048732",
    "raison_sociale": "LABORATOIRE SECONDAIRE BIOPATH HAUTS D",
    "numero voie": "8",
    "type_voie": "PL",
    "libelle_voie": "VERTE",
    "bp": "",
    "cp": "59300",
    "VILLE": "VALENCIENNES ",
    "tel": "327202323",
    "telecopie": "",
    "categorie etablissement": "611",
    "libelle categorie": "Laboratoire de Biologie Médicale",
    "siret": "78386092700020",
    "lng": "3.5280209280148",
    "lat": "50.3574918250292"
  },
  {
    "finess": "590049110",
    "raison_sociale": "LABORATOIRE SECONDAIRE  SYNLAB BIOPAJ",
    "numero voie": "25",
    "type_voie": "AV",
    "libelle_voie": "GEORGES CLEMENCEAU",
    "bp": "",
    "cp": "59300",
    "VILLE": "VALENCIENNES ",
    "tel": "327282600",
    "telecopie": "327282619",
    "categorie etablissement": "611",
    "libelle categorie": "Laboratoire de Biologie Médicale",
    "siret": "78386091900027",
    "lng": "3.52114611517079",
    "lat": "50.3602422739237"
  },
  {
    "finess": "590049128",
    "raison_sociale": "LABORATOIRE PRINCIPAL  SYNLAB BIOPAJ A",
    "numero voie": "17",
    "type_voie": "AV",
    "libelle_voie": "VAUBAN",
    "bp": "",
    "cp": "59300",
    "VILLE": "VALENCIENNES ",
    "tel": "327282530",
    "telecopie": "327282549",
    "categorie etablissement": "611",
    "libelle categorie": "Laboratoire de Biologie Médicale",
    "siret": "78386091900084",
    "lng": "3.51196038626817",
    "lat": "50.3600876886912"
  },
  {
    "finess": "590051231",
    "raison_sociale": "CLIC DU VALENCIENNOIS EST",
    "numero voie": "9",
    "type_voie": "R",
    "libelle_voie": "PRINCE TINGRY",
    "bp": "BP 80264",
    "cp": "59306",
    "VILLE": "VALENCIENNES ",
    "tel": "327275952",
    "telecopie": "327298074",
    "categorie etablissement": "463",
    "libelle categorie": "Centres Locaux Information Coordination P.A .(C.L.I.C.)",
    "siret": "44485472300012",
    "lng": "3.5183689634394",
    "lat": "50.3571233417704"
  },
  {
    "finess": "590051249",
    "raison_sociale": "CLIC DU VALENCIENNOIS OUEST",
    "numero voie": "9",
    "type_voie": "R",
    "libelle_voie": "PRINCE TINGRY",
    "bp": "BP 80264",
    "cp": "59306",
    "VILLE": "VALENCIENNES ",
    "tel": "327275952",
    "telecopie": "327298074",
    "categorie etablissement": "463",
    "libelle categorie": "Centres Locaux Information Coordination P.A .(C.L.I.C.)",
    "siret": "",
    "lng": "3.5183689634394",
    "lat": "50.3571233417704"
  },
  {
    "finess": "590051298",
    "raison_sociale": "CAU AL COYETTE ALEFPA VALENCIENNES",
    "numero voie": "3",
    "type_voie": "R",
    "libelle_voie": "DU CHAUFFOUR",
    "bp": "",
    "cp": "59300",
    "VILLE": "VALENCIENNES ",
    "tel": "327280520",
    "telecopie": "327280529",
    "categorie etablissement": "219",
    "libelle categorie": "Autre Centre d'Accueil",
    "siret": "77562407501862",
    "lng": "3.51670588585719",
    "lat": "50.3690503226489"
  },
  {
    "finess": "590051306",
    "raison_sociale": "CAU  BLAISE PASCAL SOLIHA VALENCIENNES",
    "numero voie": "3",
    "type_voie": "R",
    "libelle_voie": "BLAISE PASCAL",
    "bp": "",
    "cp": "59300",
    "VILLE": "VALENCIENNES ",
    "tel": "327299289",
    "telecopie": "",
    "categorie etablissement": "219",
    "libelle categorie": "Autre Centre d'Accueil",
    "siret": "82789379300014",
    "lng": "3.50954746334557",
    "lat": "50.3530912318938"
  },
  {
    "finess": "590051322",
    "raison_sociale": "ACCUEIL DE JOUR FONDATION ABBE PIERRE",
    "numero voie": "16",
    "type_voie": "BD",
    "libelle_voie": "FROISSART",
    "bp": "",
    "cp": "59300",
    "VILLE": "VALENCIENNES ",
    "tel": "327470748",
    "telecopie": "327450572",
    "categorie etablissement": "219",
    "libelle categorie": "Autre Centre d'Accueil",
    "siret": "34528201600285",
    "lng": "3.51934558245777",
    "lat": "50.3621621688647"
  },
  {
    "finess": "590051348",
    "raison_sociale": "CAU SIAO SECTEUR SUD VALENCIENNES",
    "numero voie": "10",
    "type_voie": "R",
    "libelle_voie": "JEAN BONMARCHE",
    "bp": "",
    "cp": "59300",
    "VILLE": "VALENCIENNES ",
    "tel": "327212079",
    "telecopie": "310384644",
    "categorie etablissement": "219",
    "libelle categorie": "Autre Centre d'Accueil",
    "siret": "44197660200041",
    "lng": "3.52505108033475",
    "lat": "50.3520611045478"
  },
  {
    "finess": "590051355",
    "raison_sociale": "CAU CROIX ROUGE FRANCAISE VALENCIENNES",
    "numero voie": "27",
    "type_voie": "R",
    "libelle_voie": "JOSQUIN DESPREZ",
    "bp": "",
    "cp": "59300",
    "VILLE": "VALENCIENNES ",
    "tel": "327462017",
    "telecopie": "327276890",
    "categorie etablissement": "219",
    "libelle categorie": "Autre Centre d'Accueil",
    "siret": "77567227213366",
    "lng": "3.51563550688706",
    "lat": "50.3704876632847"
  },
  {
    "finess": "590051587",
    "raison_sociale": "SERVICE MJPM DE CROIX MARINE",
    "numero voie": "62",
    "type_voie": "R",
    "libelle_voie": "FAUBOURG DE PARIS",
    "bp": "",
    "cp": "59300",
    "VILLE": "VALENCIENNES ",
    "tel": "327090330",
    "telecopie": "327090337",
    "categorie etablissement": "340",
    "libelle categorie": "Service mandataire judiciaire à la protection des majeurs",
    "siret": "38758140800060",
    "lng": "3.51339196694044",
    "lat": "50.3531902181966"
  },
  {
    "finess": "590051678",
    "raison_sociale": "GCS FILIERE GERIATRIQUE VALENCIENNOIS",
    "numero voie": "114",
    "type_voie": "AV",
    "libelle_voie": "DESANDROUIN",
    "bp": "",
    "cp": "59322",
    "VILLE": "VALENCIENNES ",
    "tel": "",
    "telecopie": "",
    "categorie etablissement": "696",
    "libelle categorie": "Groupement de coopération sanitaire de moyens",
    "siret": "13001555500019",
    "lng": "3.49584003556529",
    "lat": "50.3614750523127"
  },
  {
    "finess": "590052049",
    "raison_sociale": "CALIVAL",
    "numero voie": "8",
    "type_voie": "AV",
    "libelle_voie": "VAUBAN",
    "bp": "",
    "cp": "59300",
    "VILLE": "VALENCIENNES ",
    "tel": "327091010",
    "telecopie": "366227073",
    "categorie etablissement": "698",
    "libelle categorie": "Autre Etablissement Loi Hospitalière",
    "siret": "31094155400035",
    "lng": "3.51187293269394",
    "lat": "50.3604597392987"
  },
  {
    "finess": "590052205",
    "raison_sociale": "SSIAD SANTELYS VALENCIENNES",
    "numero voie": "118",
    "type_voie": "AV",
    "libelle_voie": "DÉSANDROUIN",
    "bp": "",
    "cp": "59300",
    "VILLE": "VALENCIENNES ",
    "tel": "362288000",
    "telecopie": "",
    "categorie etablissement": "354",
    "libelle categorie": "Service de Soins Infirmiers A Domicile (S.S.I.A.D)",
    "siret": "",
    "lng": "3.49584003556529",
    "lat": "50.3614750523127"
  },
  {
    "finess": "590053476",
    "raison_sociale": "SSIAD AIDE AU QUOTIDIEN",
    "numero voie": "9",
    "type_voie": "R",
    "libelle_voie": "DES GLATIGNIES",
    "bp": "",
    "cp": "59300",
    "VILLE": "VALENCIENNES ",
    "tel": "",
    "telecopie": "",
    "categorie etablissement": "354",
    "libelle categorie": "Service de Soins Infirmiers A Domicile (S.S.I.A.D)",
    "siret": "47947473600036",
    "lng": "3.51790175893967",
    "lat": "50.3582295977687"
  },
  {
    "finess": "590053898",
    "raison_sociale": "SAMSAH APF VALENCIENNES",
    "numero voie": "108",
    "type_voie": "R",
    "libelle_voie": "DE FAMARS",
    "bp": "",
    "cp": "59300",
    "VILLE": "VALENCIENNES ",
    "tel": "327469706",
    "telecopie": "327469707",
    "categorie etablissement": "445",
    "libelle categorie": "Service d'accompagnement médico-social adultes handicapés",
    "siret": "77568873210763",
    "lng": "3.52260180662641",
    "lat": "50.3532188981374"
  },
  {
    "finess": "590053906",
    "raison_sociale": "GCS SANT'HAINAUT ET SIEGE",
    "numero voie": "61",
    "type_voie": "AV",
    "libelle_voie": "DESANDROUIN",
    "bp": "",
    "cp": "59322",
    "VILLE": "VALENCIENNES ",
    "tel": "",
    "telecopie": "",
    "categorie etablissement": "696",
    "libelle categorie": "Groupement de coopération sanitaire de moyens",
    "siret": "",
    "lng": "3.502153965959",
    "lat": "50.3580540604465"
  },
  {
    "finess": "590054300",
    "raison_sociale": "GCS TRAITEMENT DU LINGE ETS DU HAINAUT",
    "numero voie": "",
    "type_voie": "",
    "libelle_voie": "",
    "bp": "",
    "cp": "59300",
    "VILLE": "VALENCIENNES ",
    "tel": "",
    "telecopie": "",
    "categorie etablissement": "696",
    "libelle categorie": "Groupement de coopération sanitaire de moyens",
    "siret": "",
    "lng": "3.5183689634394",
    "lat": "50.3571233417704"
  },
  {
    "finess": "590055448",
    "raison_sociale": "GCS SOINS CARDIO INTERV VALENCIENNOIS",
    "numero voie": "61",
    "type_voie": "AV",
    "libelle_voie": "DÉSANDROUIN",
    "bp": "",
    "cp": "59322",
    "VILLE": "VALENCIENNES ",
    "tel": "",
    "telecopie": "",
    "categorie etablissement": "696",
    "libelle categorie": "Groupement de coopération sanitaire de moyens",
    "siret": "",
    "lng": "3.502153965959",
    "lat": "50.3580540604465"
  },
  {
    "finess": "590057030",
    "raison_sociale": "GCS HOSPITALO-UNIVER HAINAUT-CAMBRESIS",
    "numero voie": "114",
    "type_voie": "AV",
    "libelle_voie": "DESANDROUINS",
    "bp": "BP 479",
    "cp": "59322",
    "VILLE": "VALENCIENNES ",
    "tel": "",
    "telecopie": "",
    "categorie etablissement": "696",
    "libelle categorie": "Groupement de coopération sanitaire de moyens",
    "siret": "13002056300016",
    "lng": "3.49584003556529",
    "lat": "50.3614750523127"
  },
  {
    "finess": "590057295",
    "raison_sociale": "SAD BG SENIORS SERVICES",
    "numero voie": "1",
    "type_voie": "AV",
    "libelle_voie": "DU SENATEUR GIRARD",
    "bp": "",
    "cp": "59300",
    "VILLE": "VALENCIENNES ",
    "tel": "",
    "telecopie": "",
    "categorie etablissement": "460",
    "libelle categorie": "Service d'Aide et d'Accompagnement à Domicile (S.A.A.D.)",
    "siret": "79847702200015",
    "lng": "3.51714507717733",
    "lat": "50.3612206420593"
  },
  {
    "finess": "590057600",
    "raison_sociale": "CSP UNIVERSITÉ POLYTECHNIQUE HDF",
    "numero voie": "",
    "type_voie": "",
    "libelle_voie": "CAMPUS LE MONT HOUY",
    "bp": "",
    "cp": "59311",
    "VILLE": "VALENCIENNES ",
    "tel": "327511045",
    "telecopie": "",
    "categorie etablissement": "124",
    "libelle categorie": "Centre de Santé",
    "siret": "19593279300019",
    "lng": "3.5183689634394",
    "lat": "50.3571233417704"
  },
  {
    "finess": "590058624",
    "raison_sociale": "SAS RESIDE ETUDES SENIORS LA GIRANDIER",
    "numero voie": "27",
    "type_voie": "R",
    "libelle_voie": "HENRY DERYCKE",
    "bp": "",
    "cp": "59300",
    "VILLE": "VALENCIENNES ",
    "tel": "327328585",
    "telecopie": "327328592",
    "categorie etablissement": "460",
    "libelle categorie": "Service d'Aide et d'Accompagnement à Domicile (S.A.A.D.)",
    "siret": "79748872300041",
    "lng": "3.52709107378595",
    "lat": "50.3649448198706"
  },
  {
    "finess": "590061750",
    "raison_sociale": "AIDE A DOMICILE",
    "numero voie": "1",
    "type_voie": "R",
    "libelle_voie": "JEANNE D'ARC",
    "bp": "",
    "cp": "59300",
    "VILLE": "VALENCIENNES ",
    "tel": "327290815",
    "telecopie": "",
    "categorie etablissement": "460",
    "libelle categorie": "Service d'Aide et d'Accompagnement à Domicile (S.A.A.D.)",
    "siret": "",
    "lng": "3.50739437482392",
    "lat": "50.3633799021497"
  },
  {
    "finess": "590061933",
    "raison_sociale": "SCM SCANNER VAUBAN VALENCIENNES",
    "numero voie": "10",
    "type_voie": "AV",
    "libelle_voie": "VAUBAN",
    "bp": "",
    "cp": "59300",
    "VILLE": "VALENCIENNES ",
    "tel": "",
    "telecopie": "",
    "categorie etablissement": "698",
    "libelle categorie": "Autre Etablissement Loi Hospitalière",
    "siret": "",
    "lng": "3.51228391239947",
    "lat": "50.3600217049871"
  },
  {
    "finess": "590061941",
    "raison_sociale": "SCM SCANNER SAMBRE ESCAUT",
    "numero voie": "8",
    "type_voie": "AV",
    "libelle_voie": "VAUBAN",
    "bp": "",
    "cp": "59300",
    "VILLE": "VALENCIENNES ",
    "tel": "",
    "telecopie": "",
    "categorie etablissement": "698",
    "libelle categorie": "Autre Etablissement Loi Hospitalière",
    "siret": "",
    "lng": "3.51187293269394",
    "lat": "50.3604597392987"
  },
  {
    "finess": "590063061",
    "raison_sociale": "SAAD ADES VALENCIENNES",
    "numero voie": "17",
    "type_voie": "QU",
    "libelle_voie": "DES MINES",
    "bp": "",
    "cp": "59300",
    "VILLE": "VALENCIENNES ",
    "tel": "320163910",
    "telecopie": "",
    "categorie etablissement": "460",
    "libelle categorie": "Service d'Aide et d'Accompagnement à Domicile (S.A.A.D.)",
    "siret": "49754177100109",
    "lng": "3.515431392091",
    "lat": "50.3665804494244"
  },
  {
    "finess": "590063525",
    "raison_sociale": "BIEN A LA MAISON (ONELA) VALENCIENNES",
    "numero voie": "2",
    "type_voie": "AV",
    "libelle_voie": "DU SERGENT CAIRNS",
    "bp": "",
    "cp": "59300",
    "VILLE": "VALENCIENNES ",
    "tel": "374029987",
    "telecopie": "",
    "categorie etablissement": "460",
    "libelle categorie": "Service d'Aide et d'Accompagnement à Domicile (S.A.A.D.)",
    "siret": "48937569101386",
    "lng": "3.52338158638428",
    "lat": "50.3516875253842"
  },
  {
    "finess": "590063665",
    "raison_sociale": "DOMICIL+NORD",
    "numero voie": "",
    "type_voie": "R",
    "libelle_voie": "DU SÉNATEUR GIRARD",
    "bp": "",
    "cp": "59300",
    "VILLE": "VALENCIENNES ",
    "tel": "",
    "telecopie": "",
    "categorie etablissement": "460",
    "libelle categorie": "Service d'Aide et d'Accompagnement à Domicile (S.A.A.D.)",
    "siret": "",
    "lng": "3.51741396625689",
    "lat": "50.3613012146749"
  },
  {
    "finess": "590063681",
    "raison_sociale": "SAD DE VITALIANCE",
    "numero voie": "",
    "type_voie": "R",
    "libelle_voie": "CARPEAUX",
    "bp": "",
    "cp": "59300",
    "VILLE": "VALENCIENNES ",
    "tel": "",
    "telecopie": "",
    "categorie etablissement": "460",
    "libelle categorie": "Service d'Aide et d'Accompagnement à Domicile (S.A.A.D.)",
    "siret": "",
    "lng": "3.51760911758383",
    "lat": "50.3604860950355"
  },
  {
    "finess": "590064119",
    "raison_sociale": "CTRE DE JOUR FROISSART - SECTEUR 59G32",
    "numero voie": "72",
    "type_voie": "BD",
    "libelle_voie": "FROISSART",
    "bp": "",
    "cp": "59300",
    "VILLE": "VALENCIENNES ",
    "tel": "",
    "telecopie": "",
    "categorie etablissement": "355",
    "libelle categorie": "Centre Hospitalier (C.H.)",
    "siret": "",
    "lng": "3.52282117547081",
    "lat": "50.3639754060188"
  },
  {
    "finess": "590064143",
    "raison_sociale": "POUPONNIERE MEF VALENCIENNOIS EPDSAE",
    "numero voie": "46",
    "type_voie": "R",
    "libelle_voie": "CLAUDIN LEJEUNE",
    "bp": "",
    "cp": "59300",
    "VILLE": "VALENCIENNES ",
    "tel": "",
    "telecopie": "",
    "categorie etablissement": "172",
    "libelle categorie": "Pouponnière à Caractère Social",
    "siret": "",
    "lng": "3.52814059276283",
    "lat": "50.3517561338988"
  },
  {
    "finess": "590064150",
    "raison_sociale": "PFS MEF VALENCIENNOIS EPDSAE",
    "numero voie": "46",
    "type_voie": "R",
    "libelle_voie": "CLAUDIN LEJEUNE",
    "bp": "",
    "cp": "59300",
    "VILLE": "VALENCIENNES ",
    "tel": "",
    "telecopie": "",
    "categorie etablissement": "236",
    "libelle categorie": "Centre Placement Familial Socio-Educatif (C.P.F.S.E.)",
    "siret": "",
    "lng": "3.52814059276283",
    "lat": "50.3517561338988"
  },
  {
    "finess": "590064325",
    "raison_sociale": "CSI VALENCIENNES",
    "numero voie": "8",
    "type_voie": "R",
    "libelle_voie": "DE L'HÔPITAL DE SIÈGE",
    "bp": "",
    "cp": "59300",
    "VILLE": "VALENCIENNES ",
    "tel": "",
    "telecopie": "",
    "categorie etablissement": "124",
    "libelle categorie": "Centre de Santé",
    "siret": "88493128800010",
    "lng": "3.52114728997129",
    "lat": "50.3524664019793"
  },
  {
    "finess": "590064416",
    "raison_sociale": "INSTITUT DE SSR JEAN STABLINSKI",
    "numero voie": "",
    "type_voie": "AV",
    "libelle_voie": "DÉSANDROUIN",
    "bp": "CS 50479",
    "cp": "59322",
    "VILLE": "VALENCIENNES ",
    "tel": "327143120",
    "telecopie": "",
    "categorie etablissement": "355",
    "libelle categorie": "Centre Hospitalier (C.H.)",
    "siret": "",
    "lng": "3.49306312133107",
    "lat": "50.3626838320403"
  },
  {
    "finess": "590064648",
    "raison_sociale": "CAU LA POSE VALENCIENNES",
    "numero voie": "9",
    "type_voie": "R",
    "libelle_voie": "ABEL DE PUJOL",
    "bp": "",
    "cp": "59300",
    "VILLE": "VALENCIENNES ",
    "tel": "327472299",
    "telecopie": "327304404",
    "categorie etablissement": "219",
    "libelle categorie": "Autre Centre d'Accueil",
    "siret": "38082649500018",
    "lng": "3.52755171454382",
    "lat": "50.3548919979753"
  },
  {
    "finess": "590064689",
    "raison_sociale": "CHU ACCUEIL DE JOUR MIDI PARTAGE",
    "numero voie": "5",
    "type_voie": "AV",
    "libelle_voie": "DU FAUBOURG DE CAMBRAI",
    "bp": "",
    "cp": "59300",
    "VILLE": "VALENCIENNES ",
    "tel": "327303666",
    "telecopie": "",
    "categorie etablissement": "219",
    "libelle categorie": "Autre Centre d'Accueil",
    "siret": "40184277800052",
    "lng": "3.51397872754354",
    "lat": "50.3453480927896"
  },
  {
    "finess": "590064929",
    "raison_sociale": "DIABHAINAUT",
    "numero voie": "53",
    "type_voie": "R",
    "libelle_voie": "DU FAUBOURG DE PARIS",
    "bp": "",
    "cp": "59300",
    "VILLE": "VALENCIENNES ",
    "tel": "",
    "telecopie": "",
    "categorie etablissement": "698",
    "libelle categorie": "Autre Etablissement Loi Hospitalière",
    "siret": "44360263600039",
    "lng": "3.51138963865205",
    "lat": "50.3532012248254"
  },
  {
    "finess": "590065223",
    "raison_sociale": "SHAB LABORATOIRE VALENCIENNES",
    "numero voie": "",
    "type_voie": "AV",
    "libelle_voie": "DESANDROUIN",
    "bp": "",
    "cp": "59300",
    "VILLE": "VALENCIENNES ",
    "tel": "",
    "telecopie": "",
    "categorie etablissement": "695",
    "libelle categorie": "Groupement de coopération sanitaire de moyens - Exploitant",
    "siret": "90793918500019",
    "lng": "3.49306312133107",
    "lat": "50.3626838320403"
  },
  {
    "finess": "590065355",
    "raison_sociale": "AED HESTIA ALEFPA VALENCIENNES",
    "numero voie": "83",
    "type_voie": "AV",
    "libelle_voie": "ALFRED GIARD",
    "bp": "",
    "cp": "59300",
    "VILLE": "VALENCIENNES ",
    "tel": "",
    "telecopie": "",
    "categorie etablissement": "295",
    "libelle categorie": "Services AEMO et AED",
    "siret": "77562407501771",
    "lng": "3.50946485049055",
    "lat": "50.3577008923773"
  },
  {
    "finess": "590065363",
    "raison_sociale": "MECS DAJ METAMORPHOSE VALENCIENNES",
    "numero voie": "26",
    "type_voie": "AV",
    "libelle_voie": "DE SAINT AMAND",
    "bp": "",
    "cp": "59300",
    "VILLE": "VALENCIENNES ",
    "tel": "",
    "telecopie": "",
    "categorie etablissement": "177",
    "libelle categorie": "Maison d'Enfants à Caractère Social",
    "siret": "77562407501888",
    "lng": "3.51375809501195",
    "lat": "50.3660110436068"
  },
  {
    "finess": "590065660",
    "raison_sociale": "MSP CHASSE ROYALE",
    "numero voie": "9",
    "type_voie": "R",
    "libelle_voie": "HECTOR BERLIOZ",
    "bp": "",
    "cp": "59300",
    "VILLE": "VALENCIENNES ",
    "tel": "609603333",
    "telecopie": "",
    "categorie etablissement": "603",
    "libelle categorie": "Maison de santé (L.6223-3)",
    "siret": "89746997900016",
    "lng": "3.48661577344179",
    "lat": "50.3542746112064"
  },
  {
    "finess": "590065884",
    "raison_sociale": "DOMICIL + NORD",
    "numero voie": "1",
    "type_voie": "AV",
    "libelle_voie": "DU SÉNATEUR GIRARD",
    "bp": "",
    "cp": "59300",
    "VILLE": "VALENCIENNES ",
    "tel": "",
    "telecopie": "",
    "categorie etablissement": "460",
    "libelle categorie": "Service d'Aide et d'Accompagnement à Domicile (S.A.A.D.)",
    "siret": "49494253500522",
    "lng": "3.51714507717733",
    "lat": "50.3612206420593"
  },
  {
    "finess": "590066338",
    "raison_sociale": "CSD VALENCIENNES",
    "numero voie": "2",
    "type_voie": "PAS",
    "libelle_voie": "DE L'ARSENAL",
    "bp": "",
    "cp": "59300",
    "VILLE": "VALENCIENNES ",
    "tel": "",
    "telecopie": "",
    "categorie etablissement": "124",
    "libelle categorie": "Centre de Santé",
    "siret": "90211799300011",
    "lng": "3.5183689634394",
    "lat": "50.3571233417704"
  },
  {
    "finess": "590066940",
    "raison_sociale": "GCS S.H.A.B. ÉTABLISSEMENT SIÈGE",
    "numero voie": "",
    "type_voie": "AV",
    "libelle_voie": "DÉSANDROUIN",
    "bp": "",
    "cp": "59300",
    "VILLE": "VALENCIENNES ",
    "tel": "",
    "telecopie": "",
    "categorie etablissement": "696",
    "libelle categorie": "Groupement de coopération sanitaire de moyens",
    "siret": "",
    "lng": "3.49306312133107",
    "lat": "50.3626838320403"
  },
  {
    "finess": "590067088",
    "raison_sociale": "S.A.A.D VITALLIANCE VALENCIENNES OUEST",
    "numero voie": "183",
    "type_voie": "AV",
    "libelle_voie": "DESANDROUINS",
    "bp": "",
    "cp": "59300",
    "VILLE": "VALENCIENNES ",
    "tel": "",
    "telecopie": "",
    "categorie etablissement": "460",
    "libelle categorie": "Service d'Aide et d'Accompagnement à Domicile (S.A.A.D.)",
    "siret": "",
    "lng": "3.49029182932895",
    "lat": "50.3633287115563"
  },
  {
    "finess": "590067096",
    "raison_sociale": "S.A.A.D VITALLIANCE VALENCIENNES EST",
    "numero voie": "183",
    "type_voie": "AV",
    "libelle_voie": "DESANDROUINS",
    "bp": "",
    "cp": "59300",
    "VILLE": "VALENCIENNES ",
    "tel": "",
    "telecopie": "",
    "categorie etablissement": "460",
    "libelle categorie": "Service d'Aide et d'Accompagnement à Domicile (S.A.A.D.)",
    "siret": "",
    "lng": "3.49029182932895",
    "lat": "50.3633287115563"
  },
  {
    "finess": "590067161",
    "raison_sociale": "LBM BIOLAM 59 VALENCIENNES",
    "numero voie": "20",
    "type_voie": "PL",
    "libelle_voie": "VERTE",
    "bp": "",
    "cp": "59300",
    "VILLE": "VALENCIENNES ",
    "tel": "",
    "telecopie": "",
    "categorie etablissement": "611",
    "libelle categorie": "Laboratoire de Biologie Médicale",
    "siret": "",
    "lng": "3.52887437445465",
    "lat": "50.3571084008199"
  },
  {
    "finess": "590067476",
    "raison_sociale": "AZAÉ HAINAUT",
    "numero voie": "44",
    "type_voie": "AV",
    "libelle_voie": "VILLARS",
    "bp": "",
    "cp": "59300",
    "VILLE": "VALENCIENNES ",
    "tel": "",
    "telecopie": "",
    "categorie etablissement": "460",
    "libelle categorie": "Service d'Aide et d'Accompagnement à Domicile (S.A.A.D.)",
    "siret": "",
    "lng": "3.5100437947179",
    "lat": "50.3583314500168"
  },
  {
    "finess": "590067773",
    "raison_sociale": "CS D'IMAGERIE MÉDICALE",
    "numero voie": "",
    "type_voie": "R",
    "libelle_voie": "DES INCAS",
    "bp": "",
    "cp": "59300",
    "VILLE": "VALENCIENNES ",
    "tel": "",
    "telecopie": "",
    "categorie etablissement": "124",
    "libelle categorie": "Centre de Santé",
    "siret": "89368632900093",
    "lng": "3.52976601544",
    "lat": "50.3571566494557"
  },
  {
    "finess": "590068409",
    "raison_sociale": "ITEP DE VALENCIENNES",
    "numero voie": "108",
    "type_voie": "AV",
    "libelle_voie": "DE CONDÉ",
    "bp": "",
    "cp": "59300",
    "VILLE": "VALENCIENNES ",
    "tel": "",
    "telecopie": "",
    "categorie etablissement": "186",
    "libelle categorie": "Institut Thérapeutique Éducatif et Pédagogique (I.T.E.P.)",
    "siret": "",
    "lng": "3.51375310234905",
    "lat": "50.3706256895696"
  },
  {
    "finess": "590068698",
    "raison_sociale": "CSP LE MARAIS",
    "numero voie": "20",
    "type_voie": "PL",
    "libelle_voie": "VERTES",
    "bp": "",
    "cp": "59300",
    "VILLE": "VALENCIENNES ",
    "tel": "366599590",
    "telecopie": "",
    "categorie etablissement": "124",
    "libelle categorie": "Centre de Santé",
    "siret": "90001386300023",
    "lng": "3.52887437445465",
    "lat": "50.3571084008199"
  },
  {
    "finess": "590068755",
    "raison_sociale": "CSP DU MUSÉE VALENCIENNES",
    "numero voie": "8",
    "type_voie": "R",
    "libelle_voie": "DES INCAS",
    "bp": "",
    "cp": "59300",
    "VILLE": "VALENCIENNES ",
    "tel": "",
    "telecopie": "",
    "categorie etablissement": "124",
    "libelle categorie": "Centre de Santé",
    "siret": "91237137400014",
    "lng": "3.52977503825387",
    "lat": "50.3570802975449"
  },
  {
    "finess": "590069217",
    "raison_sociale": "SAAD AIDE AU QUOTIDIEN",
    "numero voie": "9",
    "type_voie": "R",
    "libelle_voie": "DES GLATIGNIES",
    "bp": "",
    "cp": "59300",
    "VILLE": "VALENCIENNES ",
    "tel": "327481731",
    "telecopie": "",
    "categorie etablissement": "460",
    "libelle categorie": "Service d'Aide et d'Accompagnement à Domicile (S.A.A.D.)",
    "siret": "",
    "lng": "3.51790175893967",
    "lat": "50.3582295977687"
  },
  {
    "finess": "590069225",
    "raison_sociale": "MECS AFEJI VALENCIENNES",
    "numero voie": "108",
    "type_voie": "AV",
    "libelle_voie": "CONDÉ",
    "bp": "",
    "cp": "59300",
    "VILLE": "VALENCIENNES ",
    "tel": "",
    "telecopie": "",
    "categorie etablissement": "177",
    "libelle categorie": "Maison d'Enfants à Caractère Social",
    "siret": "",
    "lng": "3.51375310234905",
    "lat": "50.3706256895696"
  },
  {
    "finess": "590069548",
    "raison_sociale": "LABORATOIRE SECONDAIRE BIOPATH HAUTS D",
    "numero voie": "72",
    "type_voie": "AV",
    "libelle_voie": "DE DENAIN",
    "bp": "",
    "cp": "59300",
    "VILLE": "VALENCIENNES ",
    "tel": "",
    "telecopie": "",
    "categorie etablissement": "611",
    "libelle categorie": "Laboratoire de Biologie Médicale",
    "siret": "",
    "lng": "3.50091544707865",
    "lat": "50.3552911739055"
  },
  {
    "finess": "590070611",
    "raison_sociale": "SAAD DOMITYS L'ESQUISSE",
    "numero voie": "22",
    "type_voie": "CHE",
    "libelle_voie": "DE HALAGE",
    "bp": "",
    "cp": "59300",
    "VILLE": "VALENCIENNES ",
    "tel": "376310000",
    "telecopie": "",
    "categorie etablissement": "460",
    "libelle categorie": "Service d'Aide et d'Accompagnement à Domicile (S.A.A.D.)",
    "siret": "",
    "lng": "3.51631466447778",
    "lat": "50.3664815927234"
  },
  {
    "finess": "590782157",
    "raison_sociale": "CSD VALENCIENNES",
    "numero voie": "183",
    "type_voie": "AV",
    "libelle_voie": "DESANDROUINS",
    "bp": "",
    "cp": "59300",
    "VILLE": "VALENCIENNES ",
    "tel": "327228202",
    "telecopie": "",
    "categorie etablissement": "124",
    "libelle categorie": "Centre de Santé",
    "siret": "78371204501078",
    "lng": "3.49029182932895",
    "lat": "50.3633287115563"
  },
  {
    "finess": "590782181",
    "raison_sociale": "CRF LE VAL BLEU  DE VALENCIENNES",
    "numero voie": "57",
    "type_voie": "AV",
    "libelle_voie": "DESANDROUINS",
    "bp": "CS 50479",
    "cp": "59300",
    "VILLE": "VALENCIENNES ",
    "tel": "327420573",
    "telecopie": "327471840",
    "categorie etablissement": "109",
    "libelle categorie": "Etablissement de santé privé autorisé en SSR",
    "siret": "42362826200184",
    "lng": "3.5008636459216",
    "lat": "50.3587003313292"
  },
  {
    "finess": "590782256",
    "raison_sociale": "NOUVELLE CLINIQUE DES DENTELLIERES",
    "numero voie": "8",
    "type_voie": "AV",
    "libelle_voie": "VAUBAN",
    "bp": "",
    "cp": "59300",
    "VILLE": "VALENCIENNES ",
    "tel": "327147500",
    "telecopie": "327297415",
    "categorie etablissement": "129",
    "libelle categorie": "Etablissement de Soins Médicaux",
    "siret": "53270019200026",
    "lng": "3.51187293269394",
    "lat": "50.3604597392987"
  },
  {
    "finess": "590782330",
    "raison_sociale": "IME LES DEUX RIVES VALENCIENNES",
    "numero voie": "6",
    "type_voie": "R",
    "libelle_voie": "DES CENT TETES",
    "bp": "",
    "cp": "59300",
    "VILLE": "VALENCIENNES ",
    "tel": "327462030",
    "telecopie": "327338561",
    "categorie etablissement": "183",
    "libelle categorie": "Institut Médico-Educatif (I.M.E.)",
    "siret": "77562729200060",
    "lng": "3.529799156816",
    "lat": "50.3641970369562"
  },
  {
    "finess": "590782363",
    "raison_sociale": "IEM  PLAINE DE MONS",
    "numero voie": "2",
    "type_voie": "R",
    "libelle_voie": "DU CHAMP DE MANOEUVRE",
    "bp": "",
    "cp": "59300",
    "VILLE": "VALENCIENNES ",
    "tel": "327282490",
    "telecopie": "327282499",
    "categorie etablissement": "192",
    "libelle categorie": "Institut d'éducation motrice",
    "siret": "77568873201358",
    "lng": "3.53375872600249",
    "lat": "50.3611544086369"
  },
  {
    "finess": "590785374",
    "raison_sociale": "CLINIQUE TEISSIER",
    "numero voie": "118",
    "type_voie": "AV",
    "libelle_voie": "DESANDROUINS",
    "bp": "BP 333",
    "cp": "59304",
    "VILLE": "VALENCIENNES ",
    "tel": "327142434",
    "telecopie": "327142517",
    "categorie etablissement": "365",
    "libelle categorie": "Etablissement de Soins Pluridisciplinaire",
    "siret": "31245483800029",
    "lng": "3.49584003556529",
    "lat": "50.3614750523127"
  },
  {
    "finess": "590787115",
    "raison_sociale": "MECS TEMPS DE VIE VALENCIENNES",
    "numero voie": "7",
    "type_voie": "R",
    "libelle_voie": "SALLE LE COMTE",
    "bp": "",
    "cp": "59300",
    "VILLE": "VALENCIENNES ",
    "tel": "327462722",
    "telecopie": "327309648",
    "categorie etablissement": "177",
    "libelle categorie": "Maison d'Enfants à Caractère Social",
    "siret": "39434217400213",
    "lng": "3.52779601025114",
    "lat": "50.3617537405294"
  },
  {
    "finess": "590787149",
    "raison_sociale": "CHRS A.J.A.R. VALENCIENNES",
    "numero voie": "102",
    "type_voie": "AV",
    "libelle_voie": "DE REIMS",
    "bp": "BP 20374",
    "cp": "59307",
    "VILLE": "VALENCIENNES ",
    "tel": "327424484",
    "telecopie": "327424062",
    "categorie etablissement": "214",
    "libelle categorie": "Centre Hébergement & Réinsertion Sociale (C.H.R.S.)",
    "siret": "31088077800041",
    "lng": "3.52487605632436",
    "lat": "50.3472352168129"
  },
  {
    "finess": "590787156",
    "raison_sociale": "CHRS CROIX ROUGE FRANCAISE",
    "numero voie": "27",
    "type_voie": "R",
    "libelle_voie": "JOSQUIN DESPREZ",
    "bp": "",
    "cp": "59300",
    "VILLE": "VALENCIENNES ",
    "tel": "327462017",
    "telecopie": "327276890",
    "categorie etablissement": "214",
    "libelle categorie": "Centre Hébergement & Réinsertion Sociale (C.H.R.S.)",
    "siret": "77567227213366",
    "lng": "3.51563550688706",
    "lat": "50.3704876632847"
  },
  {
    "finess": "590787479",
    "raison_sociale": "RESIDENCE AUTONOMIE LOUIS DUVANT",
    "numero voie": "1",
    "type_voie": "R",
    "libelle_voie": "DE FLANDRES",
    "bp": "",
    "cp": "59300",
    "VILLE": "VALENCIENNES ",
    "tel": "327147680",
    "telecopie": "327147677",
    "categorie etablissement": "202",
    "libelle categorie": "Résidences autonomie",
    "siret": "26590673500062",
    "lng": "3.53826425893836",
    "lat": "50.3573703676125"
  },
  {
    "finess": "590787487",
    "raison_sociale": "MEF  DU VALENCIENNOIS EPDSAE",
    "numero voie": "46",
    "type_voie": "R",
    "libelle_voie": "CLAUDIN LEJEUNE",
    "bp": "BP 30003",
    "cp": "59301",
    "VILLE": "VALENCIENNES ",
    "tel": "327468212",
    "telecopie": "327410702",
    "categorie etablissement": "177",
    "libelle categorie": "Maison d'Enfants à Caractère Social",
    "siret": "26590776600116",
    "lng": "3.52814059276283",
    "lat": "50.3517561338988"
  },
  {
    "finess": "590787644",
    "raison_sociale": "IFSI CH VALENCIENNES",
    "numero voie": "114",
    "type_voie": "AV",
    "libelle_voie": "DESANDROUIN",
    "bp": "BP 479",
    "cp": "59322",
    "VILLE": "VALENCIENNES ",
    "tel": "327143636",
    "telecopie": "",
    "categorie etablissement": "300",
    "libelle categorie": "Ecoles Formant aux Professions Sanitaires",
    "siret": "26590673500120",
    "lng": "3.49584003556529",
    "lat": "50.3614750523127"
  },
  {
    "finess": "590790101",
    "raison_sociale": "EHPAD LA MAISON DES ROSES",
    "numero voie": "104",
    "type_voie": "AV",
    "libelle_voie": "DUCHESNOIS",
    "bp": "",
    "cp": "59326",
    "VILLE": "VALENCIENNES ",
    "tel": "327424200",
    "telecopie": "327420708",
    "categorie etablissement": "500",
    "libelle categorie": "Etablissement d'hébergement pour personnes âgées dépendantes",
    "siret": "",
    "lng": "3.54073992010801",
    "lat": "50.3678691481181"
  },
  {
    "finess": "590791745",
    "raison_sociale": "CAMSP APF ANZIN",
    "numero voie": "108",
    "type_voie": "R",
    "libelle_voie": "DE FAMARS",
    "bp": "",
    "cp": "59300",
    "VILLE": "VALENCIENNES ",
    "tel": "327418780",
    "telecopie": "327414559",
    "categorie etablissement": "190",
    "libelle categorie": "Centre Action Médico-Sociale Précoce (C.A.M.S.P.)",
    "siret": "77568873203115",
    "lng": "3.52260180662641",
    "lat": "50.3532188981374"
  },
  {
    "finess": "590791760",
    "raison_sociale": "CHRS LA POSE VALENCIENNES",
    "numero voie": "9",
    "type_voie": "R",
    "libelle_voie": "ABEL DE PUJOL",
    "bp": "",
    "cp": "59300",
    "VILLE": "VALENCIENNES ",
    "tel": "327472299",
    "telecopie": "327474462",
    "categorie etablissement": "214",
    "libelle categorie": "Centre Hébergement & Réinsertion Sociale (C.H.R.S.)",
    "siret": "38082649500018",
    "lng": "3.52755171454382",
    "lat": "50.3548919979753"
  },
  {
    "finess": "590794038",
    "raison_sociale": "SCE D'AIDE A DOMICILE DU CCAS",
    "numero voie": "",
    "type_voie": "PL",
    "libelle_voie": "D'ARMES",
    "bp": "BP 90339",
    "cp": "59304",
    "VILLE": "VALENCIENNES ",
    "tel": "327225909",
    "telecopie": "327225755",
    "categorie etablissement": "460",
    "libelle categorie": "Service d'Aide et d'Accompagnement à Domicile (S.A.A.D.)",
    "siret": "26590606500023",
    "lng": "3.52335331731876",
    "lat": "50.3580342250558"
  },
  {
    "finess": "590794343",
    "raison_sociale": "RESIDENCE LA TREILLE",
    "numero voie": "36",
    "type_voie": "R",
    "libelle_voie": "DE L'ABREUVOIR",
    "bp": "",
    "cp": "59300",
    "VILLE": "VALENCIENNES ",
    "tel": "327465942",
    "telecopie": "327407899",
    "categorie etablissement": "500",
    "libelle categorie": "Etablissement d'hébergement pour personnes âgées dépendantes",
    "siret": "32399622300018",
    "lng": "3.51112415936441",
    "lat": "50.3544233392058"
  },
  {
    "finess": "590794418",
    "raison_sociale": "EFS HDF-NORM - LBM VALENCIENNES",
    "numero voie": "114",
    "type_voie": "AV",
    "libelle_voie": "DESANDROUINS",
    "bp": "BP 479",
    "cp": "59322",
    "VILLE": "VALENCIENNES ",
    "tel": "328542333",
    "telecopie": "328542335",
    "categorie etablissement": "132",
    "libelle categorie": "Etablissement de Transfusion Sanguine",
    "siret": "42882285200649",
    "lng": "3.49584003556529",
    "lat": "50.3614750523127"
  },
  {
    "finess": "590796439",
    "raison_sociale": "SCE D'AIDE DOMICILE  AVAD",
    "numero voie": "11",
    "type_voie": "R",
    "libelle_voie": "DE MONS",
    "bp": "",
    "cp": "59300",
    "VILLE": "VALENCIENNES ",
    "tel": "327293169",
    "telecopie": "327459531",
    "categorie etablissement": "460",
    "libelle categorie": "Service d'Aide et d'Accompagnement à Domicile (S.A.A.D.)",
    "siret": "32642003100048",
    "lng": "3.5272487715826",
    "lat": "50.3586730405175"
  },
  {
    "finess": "590802690",
    "raison_sociale": "SERVICE AEMO ADNSEA VALENCIENNES",
    "numero voie": "6",
    "type_voie": "BD",
    "libelle_voie": "FROISSART",
    "bp": "",
    "cp": "59300",
    "VILLE": "VALENCIENNES ",
    "tel": "327283060",
    "telecopie": "327283061",
    "categorie etablissement": "295",
    "libelle categorie": "Services AEMO et AED",
    "siret": "",
    "lng": "3.51798111756963",
    "lat": "50.361452359122"
  },
  {
    "finess": "590805941",
    "raison_sociale": "CMP 59G31 & 59G32 ADUL CH VALENCIENNES",
    "numero voie": "6",
    "type_voie": "R",
    "libelle_voie": "PERCEPAIN",
    "bp": "",
    "cp": "59300",
    "VILLE": "VALENCIENNES ",
    "tel": "327200460",
    "telecopie": "327200469",
    "categorie etablissement": "156",
    "libelle categorie": "Centre Médico-Psychologique (C.M.P.)",
    "siret": "26590673500153",
    "lng": "3.52501220491803",
    "lat": "50.3618230711444"
  },
  {
    "finess": "590806063",
    "raison_sociale": "CMP 59I09 ENFANTS CH VALENCIENNES",
    "numero voie": "30",
    "type_voie": "AV",
    "libelle_voie": "SAINT-AMAND",
    "bp": "",
    "cp": "59300",
    "VILLE": "VALENCIENNES ",
    "tel": "327200480",
    "telecopie": "327200489",
    "categorie etablissement": "156",
    "libelle categorie": "Centre Médico-Psychologique (C.M.P.)",
    "siret": "26590673500161",
    "lng": "3.51322091133693",
    "lat": "50.3661883470434"
  },
  {
    "finess": "590806071",
    "raison_sociale": "CMP ENFANTS VALENCIENNES CH DENAIN",
    "numero voie": "3",
    "type_voie": "R",
    "libelle_voie": "DU FORT MINIQUE",
    "bp": "",
    "cp": "59300",
    "VILLE": "VALENCIENNES ",
    "tel": "327290202",
    "telecopie": "327453075",
    "categorie etablissement": "156",
    "libelle categorie": "Centre Médico-Psychologique (C.M.P.)",
    "siret": "26590681800074",
    "lng": "3.533111508707",
    "lat": "50.3586074565629"
  },
  {
    "finess": "590806725",
    "raison_sociale": "CATTP DE MONACO CH VALENCIENNES",
    "numero voie": "",
    "type_voie": "AV",
    "libelle_voie": "DE MONACO",
    "bp": "",
    "cp": "59300",
    "VILLE": "VALENCIENNES ",
    "tel": "327293838",
    "telecopie": "",
    "categorie etablissement": "425",
    "libelle categorie": "Centre d'Accueil Thérapeutique à temps partiel (C.A.T.T.P.)",
    "siret": "26590673500286",
    "lng": "3.50520861424594",
    "lat": "50.3595454071427"
  },
  {
    "finess": "590807103",
    "raison_sociale": "CSAPA \"LE G.R.E.I.D\"",
    "numero voie": "42",
    "type_voie": "R",
    "libelle_voie": "DE MONS",
    "bp": "",
    "cp": "59300",
    "VILLE": "VALENCIENNES ",
    "tel": "327413232",
    "telecopie": "327472864",
    "categorie etablissement": "197",
    "libelle categorie": "Centre soins accompagnement prévention addictologie (CSAPA)",
    "siret": "35148399500061",
    "lng": "3.52905541424217",
    "lat": "50.3600568988349"
  },
  {
    "finess": "590807681",
    "raison_sociale": "RESIDENCE SOCIALE FJT PRIM'TOIT",
    "numero voie": "3",
    "type_voie": "R",
    "libelle_voie": "DU PONT NEUF",
    "bp": "BP 63",
    "cp": "59300",
    "VILLE": "VALENCIENNES ",
    "tel": "327294981",
    "telecopie": "327301698",
    "categorie etablissement": "257",
    "libelle categorie": "Foyer de Jeunes Travailleurs (résidence sociale ou non)",
    "siret": "35349747200095",
    "lng": "3.52571178974509",
    "lat": "50.3609411508302"
  },
  {
    "finess": "590808416",
    "raison_sociale": "HJ PSY ENFANTS DENAIN CH VALENCIENNES",
    "numero voie": "194",
    "type_voie": "AV",
    "libelle_voie": "DE DENAIN",
    "bp": "",
    "cp": "59300",
    "VILLE": "VALENCIENNES ",
    "tel": "327200470",
    "telecopie": "327200479",
    "categorie etablissement": "355",
    "libelle categorie": "Centre Hospitalier (C.H.)",
    "siret": "26590673500211",
    "lng": "3.49383082327385",
    "lat": "50.3519152520601"
  },
  {
    "finess": "590809158",
    "raison_sociale": "MECS SOS VALENCIENNES",
    "numero voie": "168",
    "type_voie": "AV",
    "libelle_voie": "DAMPIERRE",
    "bp": "",
    "cp": "59300",
    "VILLE": "VALENCIENNES ",
    "tel": "327412211",
    "telecopie": "327471397",
    "categorie etablissement": "177",
    "libelle categorie": "Maison d'Enfants à Caractère Social",
    "siret": "77566680300157",
    "lng": "3.50800264402323",
    "lat": "50.3623171064222"
  },
  {
    "finess": "590810800",
    "raison_sociale": "PÔLE HABITAT DU VALENCIENNOIS - FL",
    "numero voie": "6",
    "type_voie": "R",
    "libelle_voie": "WEDIERE",
    "bp": "",
    "cp": "59300",
    "VILLE": "VALENCIENNES ",
    "tel": "327337079",
    "telecopie": "327478790",
    "categorie etablissement": "252",
    "libelle categorie": "Foyer Hébergement Adultes Handicapés",
    "siret": "",
    "lng": "3.52788755264552",
    "lat": "50.3608438809121"
  },
  {
    "finess": "590812749",
    "raison_sociale": "USLD CH VALENCIENNES",
    "numero voie": "",
    "type_voie": "PL",
    "libelle_voie": "DE LA CONCORDE",
    "bp": "",
    "cp": "59300",
    "VILLE": "VALENCIENNES ",
    "tel": "327147680",
    "telecopie": "327147677",
    "categorie etablissement": "362",
    "libelle categorie": "Etablissement de Soins Longue Durée",
    "siret": "26590673500245",
    "lng": "3.49952210396381",
    "lat": "50.3635368023811"
  },
  {
    "finess": "590812798",
    "raison_sociale": "MECS DECLIC'ADOS ALEFPA",
    "numero voie": "39",
    "type_voie": "AV",
    "libelle_voie": "VILLARS",
    "bp": "",
    "cp": "59300",
    "VILLE": "VALENCIENNES ",
    "tel": "327203890",
    "telecopie": "327280529",
    "categorie etablissement": "177",
    "libelle categorie": "Maison d'Enfants à Caractère Social",
    "siret": "77562407501813",
    "lng": "3.50924247360683",
    "lat": "50.3579154864171"
  },
  {
    "finess": "590813184",
    "raison_sociale": "CENTRE MATERN. ET PARENT. TEMPS DE VIE",
    "numero voie": "10",
    "type_voie": "R",
    "libelle_voie": "D'ARTOIS",
    "bp": "",
    "cp": "59300",
    "VILLE": "VALENCIENNES ",
    "tel": "327215757",
    "telecopie": "327215750",
    "categorie etablissement": "166",
    "libelle categorie": "Etablissement d'Accueil Mère-Enfant",
    "siret": "39434217400197",
    "lng": "3.5353727053138",
    "lat": "50.3551940987156"
  }
]